Workbook

Sheet Лист1
B1: РД | C1: Старший НК (1ТС) | D1: НК (1ТС) | E1: Главный Механик (1ТС) | F1: Механик (1ТС) | G1: Старший контроллёр | H1: контроллёр | I1: специалист док.обеспечения | J1: курьер
A2: Норма управляемости | B2: 1500 | C2: 70 | D2: 70 | E2: 120 | F2: 120 | G2: - | H2: - | I2: - | J2: -
A3: оклад | B3: фикс | C3: 1100 | D3: 1000 | E3: 350 | F3: 250 | G3: 70000 | H3: 55000 | I3: 40000 | J3: 45000
A4: премия | B4: - | C4: 1500 | D4: 1500 | E4: 1050 | F4: 1050 | G4: - | H4: - | I4: - | J4: -
A5: итого при 100%: | C5: 2600 | D5: 2500 | E5: 1400 | F5: 1300
A7: при при 120%: | C7: =C5*1.2 -> 3120 | D7: =D5*1.2 -> 3000 | E7: =E5*1.2 -> 1680 | F7: =F5*1.2 -> 1560

Sheet СВОД
B1: зам дир-ра по производству | C1: РД | D1: ='НК, РГ'!#REF! -> #REF! | E1: ='НК, РГ'!C20 -> Мулындин Д.М. | F1: ='НК, РГ'!C21 -> Рашитов Р.К. | G1: ='НК, РГ'!#REF! -> #REF! | H1: ='НК, РГ'!#REF! -> #REF! | I1: ='НК, РГ'!#REF! -> #REF! | J1: ='НК, РГ'!#REF! -> #REF! | K1: ='НК, РГ'!#REF! -> #REF! | L1: ='НК, РГ'!#REF! -> #REF! | M1: ='НК, РГ'!C41 -> Веденяпин Сергей Юрьевич | N1: ='НК, РГ'!C38 -> Зыков Андрей Юрьевич | O1: Главный Механик (1ТС) | P1: =контролеры!#REF! -> #REF! | Q1: =механики!C26 -> Набиев Рустам Нариманович | R1: =механики!C27 -> 0 | S1: =механики!C28 -> 0 | T1: Старший контролёр | U1: =контролеры!C21 -> Базыгутдинов Дамир Асафутдинович | V1: =контролеры!#REF! -> #REF! | W1: =контролеры!#REF! -> #REF! | X1: ='СПТД, курьер'!C8 -> Фалахова Алсу Халиловна | Y1: ='СПТД, курьер'!C7 -> Тагиров Искандер Маратович | Z1: ='СПТД, курьер'!C11 -> Костин С.В. | AA1: ИТОГО по департаменту
A2: управляемость ТС | C2: ='НК, РГ'!D44 -> 333 | D2: ='НК, РГ'!#REF! -> #REF! | E2: ='НК, РГ'!D20 -> 130 | F2: ='НК, РГ'!D21 -> 135 | G2: ='НК, РГ'!#REF! -> #REF! | H2: ='НК, РГ'!#REF! -> #REF! | I2: ='НК, РГ'!#REF! -> #REF! | J2: ='НК, РГ'!#REF! -> #REF! | K2: ='НК, РГ'!#REF! -> #REF! | L2: ='НК, РГ'!#REF! -> #REF! | M2: ='НК, РГ'!D41 -> 0 | N2: ='НК, РГ'!D38 -> 30 | O2: =C2 -> 333 | P2: =контролеры!#REF! -> #REF! | Q2: =механики!D26 -> 0 | V2: - | W2: - | X2: - | Z2: - | AA2: =C2 -> 333
A3: оклад | B3: =#REF! -> #REF! | C3: =РД!D10 -> 200000 | D3: ='НК, РГ'!#REF! -> #REF! | E3: ='НК, РГ'!F20 -> 150000 | F3: ='НК, РГ'!F21 -> 150000 | G3: ='НК, РГ'!#REF! -> #REF! | H3: ='НК, РГ'!#REF! -> #REF! | I3: ='НК, РГ'!#REF! -> #REF! | J3: ='НК, РГ'!#REF! -> #REF! | K3: ='НК, РГ'!#REF! -> #REF! | L3: ='НК, РГ'!#REF! -> #REF! | M3: ='НК, РГ'!F41 -> 37500 | N3: ='НК, РГ'!F38 -> 50000 | O3: =механики!#REF! -> #REF! | P3: =контролеры!#REF! -> #REF! | Q3: =механики!F26 -> 70000 | R3: =механики!F27 -> 0 | S3: =механики!F28 -> 0 | T3: =контролеры!D18 -> 54761.9 | U3: =контролеры!D21 -> 45000 | V3: =контролеры!#REF! -> #REF! | W3: =контролеры!#REF! -> #REF! | X3: ='СПТД, курьер'!D8 -> 30000 | Y3: ='СПТД, курьер'!D7 -> 47400 | Z3: ='СПТД, курьер'!D11 -> 30000 | AA3: =SUM(B3:Z3) -> #REF!
A4: премия | B4: =#REF! -> #REF! | C4: =РД!G10 -> 0 | D4: ='НК, РГ'!#REF! -> #REF! | E4: ='НК, РГ'!Q20 -> 0 | F4: ='НК, РГ'!Q21 -> 0 | G4: ='НК, РГ'!#REF! -> #REF! | H4: ='НК, РГ'!#REF! -> #REF! | I4: ='НК, РГ'!#REF! -> #REF! | J4: ='НК, РГ'!#REF! -> #REF! | K4: ='НК, РГ'!#REF! -> #REF! | L4: ='НК, РГ'!#REF! -> #REF! | M4: ='НК, РГ'!U41 -> 37500 | N4: ='НК, РГ'!U38 -> 42000 | O4: =механики!#REF! -> #REF! | P4: =контролеры!#REF! -> #REF! | Q4: =механики!S26 -> 0 | R4: 0 | S4: 0 | T4: =контролеры!L18 -> 40000 | U4: =контролеры!L21 -> 30000 | V4: =контролеры!#REF! -> #REF! | W4: =контролеры!#REF! -> #REF! | X4: ='СПТД, курьер'!O8 -> 40000 | Z4: ='СПТД, курьер'!O11 -> 40000 | AA4: =SUM(B4:Z4) -> #REF!
A5: ИТОГО ЗП | B5: =B3+B4 -> #REF! | C5: =C3+C4 -> 200000 | D5: =D3+D4 -> #REF! | E5: =E3+E4 -> 150000 | F5: =F3+F4 -> 150000 | G5: =G3+G4 -> #REF! | H5: =H3+H4 -> #REF! | I5: =I3+I4 -> #REF! | ... Z5: =Z3+Z4 -> 70000 | AA5: =SUM(B5:Z5) -> #REF!
A6: зп на 1ТС | C6: =C5/C2 -> 600.6006 | D6: =D5/D2 -> #REF! | E6: =E5/E2 -> 1153.8462 | F6: =F5/F2 -> 1111.1111 | G6: =G5/G2 -> #REF! | O6: =O5/O2 -> #REF! | P6: =P5/P2 -> #REF! | Q6: =Q5/Q2 -> #DIV/0! | AA6: =AA5/AA2 -> #REF!
A8: зп на 1 ТС по НК | D8: =(D5+E5+F5+G5+H5)/C2 -> #REF! | F8: =(D5+E5+F5)/C2 -> #REF! | G8: без НК 5,6
A10: зп на 1 ТС по механикам | D10: =(O5+P5+Q5)/C2 -> #REF!
A12: зп на 1Тс по контролерам | D12: =(T5+U5+V5)/C2 -> #REF!

Sheet РД
A1: РД4
A6: № п/п | B6: Должность | C6: ФИО | D6: Оклад | E6: Премия | K6: Итого начислено | L6: Удержания (штрафы, претензии) | M6: Итого к получению
D7: Начислен оклад | E7: Базовая премия | H7: KPI 1 | I7: KPI 2 | J7: KPI 3
E8: ЧФР | F8: % премии | G8: Сумма
A10: 1 | B10: РД4 | C10: Кутилин Р.В. | D10: 200000 | F10: 0.12 | G10: =E10*F10 -> 0 | K10: =D10+G10 -> 200000 | M10: =K10-L10 -> 200000

Sheet НООВ
C2: KPI
A4: Цель | C4: Оклад | D4: 50000 | E4: 50000 | F4: 50000 | G4: 50000
C5: KPI
A6: Обучать водителей экономичному вождению. Выявлять и устранять неисправности топливной системы | C6: % пережога по парку | D6: свыше 2-х% | E6: от 2х до 1,5% | F6: от 1,49 до 1% | G6: менее 1%
B7: 1 | D7: 0 | E7: 50000 | F7: 100000 | G7: 150000
A8: Найти причину пережога. Пресекать хищения топлива водителями. | B8: 2 | C8: При факте слива топлива компания получила возмещение от виновника | D8: 50000 | E8: 50000 | F8: 50000 | G8: 50000
A9: Снизить текучесть водителей в период адаптации | B9: 3 | C9: Доля уволенных водителей в течении 3-х месяцев не более | D9: более 15% | E9: от 15 до 10% | F9: менее 10%
D10: 0 | E10: 50000 | F10: 100000
C14: Прогноз достижения результата
C16: Оклад
C17: KPI
C18: Выполнение смарт задач
C20: Задачи № 1-3 | D20: 1
C21: Задачи № 4-6 | D21: 1
C22: Итого премия | E22: =E20+E21 -> 0
C23: Итого ЗП: | E23: =E16+E22 -> 0

Sheet НК, РГ
A1: Калькулятор расчета зарплаты начальникам колонн
A3: Справочные коэффициенты для РГ и НК
M4: Начальник автоколонны НЧ и филиалы | V4: Руководитель группы
B5: тарифная ставка | C5: р/тс | F5: Укомплектованность (отношение явочного коэф водителя к кол-ву ТС) | G5: Пробег (км) | H5: Средний Расход ГСМ | K5: Затраты на ТОиР (р/км) | M5: Процент выполнения плана и коэффициент: | O5: менее 93% | P5: 93-94,99% | Q5: 95-97,99% | R5: 98-100% | S5: 100% и более | V5: Процент выполнения плана и коэффициент: | X5: менее 92% | Y5: 92-94,99% | Z5: 95-97,99% | AA5: 98-99,99% | AB5: 100% и более
B6: старший НК | C6: 1100 | E6: План | F6: 1.5 | G6: 18600 | H6: Тягач 20,5л П/п 5,5л Тоннаж 20т*0,3=6 Сез.надбавка 26*10%=2.6л Итого: 34,6л (справочно) | K6: 5.92 | M6: Показатель | N6: Вес | V6: Показатель | W6: Вес
B7: НК | C7: 1000 | M7: Пробег | N7: 1000 | O7: 0.4 | P7: 0.6 | Q7: 0.8 | R7: 1 | S7: 1.2 | V7: Пробег | W7: 50000 | X7: 0.4 | Y7: 0.6 | Z7: 0.8 | AA7: 1 | AB7: 1.2
M8: Затраты на ТО и Р | N8: 1000 | O8: более 130% | P8: 129,99-120 | Q8: 119,99-110 | R8: 109,99-100,9 | S8: менее или =100% | X8: менее 95% | Y8: 95-95,99 | Z8: 96-96,99 | AA8: 97-97,99 | AB8: 98-100
B9: повышающий коэффициент за готовность ТС к МАП | O9: 0.4 | P9: 0.6 | Q9: 0.8 | R9: 1 | S9: 1.2 | V9: КТГ (98%) с учетом ДТП | W9: 50000 | X9: 0.4 | Y9: 0.6 | Z9: 0.8 | AA9: 1 | AB9: 1.2
B10: 15-30% | C10: 1.1 | M10: Укомплектованность (отношение явочного коэф водителя к кол-ву ТС) | N10: 1000 | O10: менее 90% | P10: 90-92,99 | Q10: 93-95,99 | R10: 96-99,99 | S10: 100% и более | X10: менее 96% | Y10: 96-96,99 | Z10: 97-97,99 | AA10: 98-99,5 | AB10: 99,05-100
B11: 31-50% | C11: 1.2 | O11: 0.4 | P11: 0.6 | Q11: 0.8 | R11: 1 | S11: 1.2 | V11: КВЛ (99,5%) | W11: 50000 | X11: 0.4 | Y11: 0.6 | Z11: 0.8 | AA11: 1 | AB11: 1.2
B12: более 51% | C12: 1.3 | M12: Доля МАП, чел | O12: от 1 до 3 | P12: от 4 до 5 | Q12: от 6 до 7 | R12: от 8 до 10 | S12: более 10 | V12: Доля МАП, чел | X12: от 1 до 5 | Y12: от 6 до 10 | Z12: от 11 до 15 | AA12: от 16 до 20 | AB12: более 20
O13: 5000 | P13: 10000 | Q13: 15000 | R13: 20000 | S13: 25000 | X13: 5000 | Y13: 10000 | Z13: 20000 | AA13: 30000 | AB13: 40000
A16: № п/п | B16: Должность | C16: ФИО | D16: Оклад | G16: Премия | R16: ИТОГО зарплата | S16: Удержания | T16: Премия к выплате
G17: Уровни выполнени КПЭ и ставка вознаграждения
G18: Выполнение плана по Марже | P18: Итоговая ставка вознаграждения | Q18: ИТОГО ПРЕМИЯ
D19: кол-во ТС | E19: ставка р/тс | F19: начислен оклад | G19: План по маржинальной прибыли | H19: Факт по маржинальной прибыли | I19: Сумма перевыполнения | J19: % премии | N19: Наличие премии в зависимости от перевыполнения плана по прибыли "0"-нет, "1"-да
A20: 1 | B20: РГ1 | C20: Мулындин Д.М. | D20: =D52+D54 -> 130 | F20: 150000 | G20: =M52+M54 -> 51540781 | H20: =N52+N54 -> 40331494 | I20: =H20-G20 -> -11209287 | J20: 0.02 | N20: 0 | P20: =I20*J20*N20 -> 0 | Q20: =P20 -> 0 | R20: =F20+Q20 -> 150000 | T20: =Q20-S20 -> 0
A21: 2 | B21: РГ2 | C21: Рашитов Р.К. | D21: =D55+D56 -> 135 | F21: 150000 | G21: =M55+M56 -> 49523193 | H21: =N55+N56 -> 43846196 | I21: =H21-G21 -> -5676997.6 | J21: 0.02 | N21: 0 | P21: =I21*J21*N21 -> 0 | Q21: =P21 -> 0 | R21: =F21+Q21 -> 150000 | T21: =Q21-S21 -> 0
A22: 3 | B22: РГ3 | C22: Бикмуллин Айрат Равилевич | D22: =D53+D57 -> 92 | F22: ='Д4-ФОТ '!Y9 -> 150000 | J22: 0.02 | N22: 0 | P22: =I22*J22*N22 -> 0 | Q22: =P22 -> 0 | R22: =F22+Q22 -> 150000 | T22: =Q22-S22 -> 0
D23: =SUM(D20:D22) -> 357 | E23: =SUM(E20:E22) -> 0 | F23: =SUM(F20:F22) -> 450000 | G23: =SUM(G20:G22) -> 1.0106397e+08 | H23: =SUM(H20:H22) -> 84177690 | I23: =SUM(I20:I22) -> -16886285 | Q23: =SUM(Q20:Q22) -> 0 | R23: =SUM(R20:R22) -> 450000 | S23: =SUM(S20:S22) -> 0 | T23: =SUM(T20:T22) -> 0
B25: ДЕЙСТВУЮЩАЯ СИСТЕМА МОТИВАЦИИ
A26: № п/п | B26: Должность | C26: ФИО | D26: Оклад | G26: Премия | V26: Доплаты (согл. достигнутых показателей) | W26: ИТОГО зарплата
G27: Уровни выполнени КПЭ и ставка вознаграждения
G28: =M7 -> Пробег | J28: =M8 -> Затраты на ТО и Р | N28: =M10 -> Укомплектованность (отношение явочного коэф водителя к кол-ву ТС) | Q28: Доля МАП, чел | S28: Итоговая ставка вознаграждения | T28: Доплата для доведения минимальной крышки в случае недостижения KPI | U28: ИТОГО ПРЕМИЯ
D29: кол-во ТС | E29: ставка р/тс | F29: начислен оклад | G29: Факт на 1ТС | H29: Уровень выполнения КПЭ | I29: ставка вознаграждения | J29: План | K29: Факт | L29: Уровень выполнения КПЭ (экономия менее 100%, перерасход более 100%) | M29: ставка вознаграждения | N29: Факт | O29: Уровень выполнения КПЭ | P29: ставка вознаграждения | Q29: кол-во | R29: ставка вознаграждения
A30: 1 | B30: НК3 | C30: Хузин | D30: 38 | E30: 1000 | F30: =D30*E30 -> 38000 | G30: 15651.36 | H30: =G30/$G$6 -> 0.84147097 | I30: =$N$7*IF(H30<93%,$O$7,IF(H30<95%,$P$7,IF(H30<98%,$Q$7,IF(H30<100%,$R$7,IF(H30>=100%,$S$7))))) -> 400 | J30: =4.83*2 -> 9.66 | K30: =6.29*2 -> 12.58 | L30: =K30/J30 -> 1.3022774 | M30: =$N$8*IF(L30>130%,$O$9,IF(L30>120%,$P$9,IF(L30>110%,$Q$9,IF(L30>100%,$R$9,IF(L30<=100%,S9))))) -> 400 | N30: 1.08 | O30: =N30/$F$6 -> 0.72 | P30: =$N$10*IF(O30<90%,$O$11,IF(O30<93%,$P$11,IF(O30<96%,$Q$11,IF(O30<100%,$R$11,IF(O30>=100%,$S$11))))) -> 400 | Q30: 1 | R30: =IF(Q30<1,0,IF(Q30<=3,$O$13,IF(Q30<=5,$P$13,IF(Q30<=7,$Q$13,IF(Q30<=10,$R$13,IF(Q30>10,$S$13)))))) -> 5000 | S30: =I30+M30+P30 -> 1200 | U30: =S30*D30+R30+T30 -> 50600 | W30: =F30+U30 -> 88600 | AD30: =X30+Y30+Z30+AA30+AB30+#REF! -> #REF!
A31: 3 | B31: НК8 | C31: Набиуллин | D31: 40 | F31: 50000 | G31: 17362.38 | H31: =G31/$G$6 -> 0.93346129 | I31: =$N$7*IF(H31<93%,$O$7,IF(H31<95%,$P$7,IF(H31<98%,$Q$7,IF(H31<100%,$R$7,IF(H31>=100%,$S$7))))) -> 600 | J31: =4.41*2 -> 8.82 | K31: =5.15*2 -> 10.3 | L31: =K31/J31 -> 1.1678005 | M31: =$N$8*IF(L31>130%,$O$9,IF(L31>120%,$P$9,IF(L31>110%,$Q$9,IF(L31>100%,$R$9,IF(L31<=100%,S10))))) -> 800 | N31: 1.21 | O31: =N31/$F$6 -> 0.80666667 | P31: =$N$10*IF(O31<90%,$O$11,IF(O31<93%,$P$11,IF(O31<96%,$Q$11,IF(O31<100%,$R$11,IF(O31>=100%,$S$11))))) -> 400 | Q31: 1 | R31: =IF(Q31<1,0,IF(Q31<=3,$O$13,IF(Q31<=5,$P$13,IF(Q31<=7,$Q$13,IF(Q31<=10,$R$13,IF(Q31>10,$S$13)))))) -> 5000 | S31: =I31+M31+P31 -> 1800 | U31: =S31*D31+R31+T31 -> 77000 | W31: =F31+U31+V31 -> 127000 | AD31: =X31+Y31+Z31+AA31+AB31+#REF! -> #REF!
A32: 11 | B32: НК12 | C32: Попов Андрей Викторович | D32: 21 | F32: 50000 | G32: 17312.24 | H32: =G32/$G$6 -> 0.93076559 | I32: =$N$7*IF(H32<93%,$O$7,IF(H32<95%,$P$7,IF(H32<98%,$Q$7,IF(H32<100%,$R$7,IF(H32>=100%,$S$7))))) -> 600 | J32: =4.44*2 -> 8.88 | K32: =6.63*2 -> 13.26 | L32: =K32/J32 -> 1.4932432 | M32: =$N$8*IF(L32>130%,$O$9,IF(L32>120%,$P$9,IF(L32>110%,$Q$9,IF(L32>100%,$R$9,IF(L32<=100%,S11))))) -> 400 | N32: 1.38 | O32: =N32/$F$6 -> 0.92 | P32: =$N$10*IF(O32<90%,$O$11,IF(O32<93%,$P$11,IF(O32<96%,$Q$11,IF(O32<100%,$R$11,IF(O32>=100%,$S$11))))) -> 600 | Q32: 0 | R32: =IF(Q32<1,0,IF(Q32<=3,$O$13,IF(Q32<=5,$P$13,IF(Q32<=7,$Q$13,IF(Q32<=10,$R$13,IF(Q32>10,$S$13)))))) -> 0 | S32: =I32+M32+P32 -> 1600 | U32: =S32*D32+R32+T32 -> 33600 | W32: =F32+U32 -> 83600 | AD32: =X32+Y32+Z32+AA32+AB32+#REF! -> #REF!
A33: 14 | B33: Нк14 | C33: Ардашов Дмитрий Сергеевич | D33: 25 | F33: 47500 | G33: 15907.47 | H33: =G33/$G$6 -> 0.85524032 | I33: =$N$7*IF(H33<93%,$O$7,IF(H33<95%,$P$7,IF(H33<98%,$Q$7,IF(H33<100%,$R$7,IF(H33>=100%,$S$7))))) -> 400 | J33: =3.5*2 -> 7 | K33: =6.47*2 -> 12.94 | L33: =K33/J33 -> 1.8485714 | M33: =$N$8*IF(L33>130%,$O$9,IF(L33>120%,$P$9,IF(L33>110%,$Q$9,IF(L33>100%,$R$9,IF(L33<=100%,S12))))) -> 400 | N33: 1.08 | O33: =N33/$F$6 -> 0.72 | P33: =$N$10*IF(O33<90%,$O$11,IF(O33<93%,$P$11,IF(O33<96%,$Q$11,IF(O33<100%,$R$11,IF(O33>=100%,$S$11))))) -> 400 | Q33: 0 | R33: =IF(Q33<1,0,IF(Q33<=3,$O$13,IF(Q33<=5,$P$13,IF(Q33<=7,$Q$13,IF(Q33<=10,$R$13,IF(Q33>10,$S$13)))))) -> 0 | S33: =I33+M33+P33 -> 1200 | U33: =S33*D33+R33+T33 -> 30000 | W33: =F33+U33+V33 -> 77500 | AD33: =X33+Y33+Z33+AA33+AB33+#REF! -> #REF!
A34: 6 | B34: НК2 | C34: Пахулин Андрей Михайлович | D34: 18 | F34: 50000 | G34: 8345.5 | H34: =G34/$G$6 -> 0.4486828 | I34: =$N$7*IF(H34<93%,$O$7,IF(H34<95%,$P$7,IF(H34<98%,$Q$7,IF(H34<100%,$R$7,IF(H34>=100%,$S$7))))) -> 400 | J34: =3.97*2 -> 7.94 | K34: =6.24*2 -> 12.48 | L34: =K34/J34 -> 1.5717884 | M34: =$N$8*IF(L34>130%,$O$9,IF(L34>120%,$P$9,IF(L34>110%,$Q$9,IF(L34>100%,$R$9,IF(L34<=100%,S13))))) -> 400 | N34: 0.68 | O34: =N34/$F$6 -> 0.45333333 | P34: =$N$10*IF(O34<90%,$O$11,IF(O34<93%,$P$11,IF(O34<96%,$Q$11,IF(O34<100%,$R$11,IF(O34>=100%,$S$11))))) -> 400 | Q34: 0 | R34: =IF(Q34<1,0,IF(Q34<=3,$O$13,IF(Q34<=5,$P$13,IF(Q34<=7,$Q$13,IF(Q34<=10,$R$13,IF(Q34>10,$S$13)))))) -> 0 | S34: =I34+M34+P34 -> 1200 | U34: =S34*D34+R34+T34 -> 21600 | W34: =F34+U34+V34 -> 71600 | AD34: =X34+Y34+Z34+AA34+AB34+#REF! -> #REF!
B35: НК13 | C35: Базыгутдинов Дамир | D35: 39 | E35: 1000 | F35: =D35*E35 -> 39000 | G35: 12044.65 | H35: =G35/$G$6 -> 0.64756183 | I35: =$N$7*IF(H35<93%,$O$7,IF(H35<95%,$P$7,IF(H35<98%,$Q$7,IF(H35<100%,$R$7,IF(H35>=100%,$S$7))))) -> 400 | J35: =4.78*2 -> 9.56 | K35: =5.88*2 -> 11.76 | L35: =K35/J35 -> 1.2301255 | M35: =$N$8*IF(L35>130%,$O$9,IF(L35>120%,$P$9,IF(L35>110%,$Q$9,IF(L35>100%,$R$9,IF(L35<=100%,S14))))) -> 600 | N35: 0.9 | O35: =N35/$F$6 -> 0.6 | P35: =$N$10*IF(O35<90%,$O$11,IF(O35<93%,$P$11,IF(O35<96%,$Q$11,IF(O35<100%,$R$11,IF(O35>=100%,$S$11))))) -> 400 | Q35: 2 | R35: =IF(Q35<1,0,IF(Q35<=3,$O$13,IF(Q35<=5,$P$13,IF(Q35<=7,$Q$13,IF(Q35<=10,$R$13,IF(Q35>10,$S$13)))))) -> 5000 | S35: =I35+M35+P35 -> 1400 | U35: =S35*D35+R35+T35 -> 59600 | W35: =F35+U35 -> 98600
A36: 2 | B36: НК7 | C36: Токунов Михаил Сергеевич | F36: 13791.4 | H36: =G36/$G$6 -> 0 | I36: =$N$7*IF(H36<93%,$O$7,IF(H36<95%,$P$7,IF(H36<98%,$Q$7,IF(H36<100%,$R$7,IF(H36>=100%,$S$7))))) -> 400 | O36: =N36/$F$6 -> 0 | P36: =$N$10*IF(O36<90%,$O$11,IF(O36<93%,$P$11,IF(O36<96%,$Q$11,IF(O36<100%,$R$11,IF(O36>=100%,$S$11))))) -> 400 | Q36: 0 | R36: =IF(Q36<1,0,IF(Q36<=3,$O$13,IF(Q36<=5,$P$13,IF(Q36<=7,$Q$13,IF(Q36<=10,$R$13,IF(Q36>10,$S$13)))))) -> 0 | S36: =I36+M36+P36 -> 800 | U36: =S36*D36+R36+T36 -> 0 | W36: =F36+U36+V36 -> 13791.4 | AD36: =X36+Y36+Z36+AA36+AB36+#REF! -> #REF!
A37: 5 | B37: НК4 | C37: Кочетов А.В. | D37: 61 | E37: 1000 | F37: =D37*E37 -> 61000 | G37: 18253.55 | H37: =G37/$G$6 -> 0.98137366 | I37: =$N$7*IF(H37<93%,$O$7,IF(H37<95%,$P$7,IF(H37<98%,$Q$7,IF(H37<100%,$R$7,IF(H37>=100%,$S$7))))) -> 1000 | J37: =4.93*2 -> 9.86 | K37: =5.3*2 -> 10.6 | L37: =K37/J37 -> 1.0750507 | M37: =$N$8*IF(L37>130%,$O$9,IF(L37>120%,$P$9,IF(L37>110%,$Q$9,IF(L37>100%,$R$9,IF(L37<=100%,S16))))) -> 1000 | N37: 1.39 | O37: =N37/$F$6 -> 0.92666667 | P37: =$N$10*IF(O37<90%,$O$11,IF(O37<93%,$P$11,IF(O37<96%,$Q$11,IF(O37<100%,$R$11,IF(O37>=100%,$S$11))))) -> 600 | Q37: 3 | R37: =IF(Q37<1,0,IF(Q37<=3,$O$13,IF(Q37<=5,$P$13,IF(Q37<=7,$Q$13,IF(Q37<=10,$R$13,IF(Q37>10,$S$13)))))) -> 5000 | S37: =I37+M37+P37 -> 2600 | U37: =S37*D37+R37+T37 -> 163600 | W37: =F37+U37 -> 224600 | AD37: =X37+Y37+Z37+AA37+AB37+#REF! -> #REF!
A38: 7 | B38: НК9 | C38: Зыков Андрей Юрьевич | D38: 30 | F38: 50000 | G38: 16762.82 | H38: =G38/$G$6 -> 0.90122688 | I38: =$N$7*IF(H38<93%,$O$7,IF(H38<95%,$P$7,IF(H38<98%,$Q$7,IF(H38<100%,$R$7,IF(H38>=100%,$S$7))))) -> 400 | J38: =3.95*2 -> 7.9 | K38: =4.85*2 -> 9.7 | L38: =K38/J38 -> 1.2278481 | M38: =$N$8*IF(L38>130%,$O$9,IF(L38>120%,$P$9,IF(L38>110%,$Q$9,IF(L38>100%,$R$9,IF(L38<=100%,S17))))) -> 600 | N38: 1.16 | O38: =N38/$F$6 -> 0.77333333 | P38: =$N$10*IF(O38<90%,$O$11,IF(O38<93%,$P$11,IF(O38<96%,$Q$11,IF(O38<100%,$R$11,IF(O38>=100%,$S$11))))) -> 400 | Q38: 0 | R38: =IF(Q38<1,0,IF(Q38<=3,$O$13,IF(Q38<=5,$P$13,IF(Q38<=7,$Q$13,IF(Q38<=10,$R$13,IF(Q38>10,$S$13)))))) -> 0 | S38: =I38+M38+P38 -> 1400 | U38: =S38*D38+R38+T38 -> 42000 | W38: =F38+U38 -> 92000 | AD38: =X38+Y38+Z38+AA38+AB38+#REF! -> #REF!
A39: 10 | B39: НК5 | C39: Кабильков Евгений Михайлович | D39: 30 | F39: 35117.59 | G39: 15386.59 | H39: =G39/$G$6 -> 0.82723602 | I39: =$N$7*IF(H39<93%,$O$7,IF(H39<95%,$P$7,IF(H39<98%,$Q$7,IF(H39<100%,$R$7,IF(H39>=100%,$S$7))))) -> 400 | J39: =3.96*2 -> 7.92 | K39: =4.5*2 -> 9 | L39: =K39/J39 -> 1.1363636 | M39: =$N$8*IF(L39>130%,$O$9,IF(L39>120%,$P$9,IF(L39>110%,$Q$9,IF(L39>100%,$R$9,IF(L39<=100%,S18))))) -> 800 | N39: 1.17 | O39: =N39/$F$6 -> 0.78 | P39: =$N$10*IF(O39<90%,$O$11,IF(O39<93%,$P$11,IF(O39<96%,$Q$11,IF(O39<100%,$R$11,IF(O39>=100%,$S$11))))) -> 400 | Q39: 2 | R39: =IF(Q39<1,0,IF(Q39<=3,$O$13,IF(Q39<=5,$P$13,IF(Q39<=7,$Q$13,IF(Q39<=10,$R$13,IF(Q39>10,$S$13)))))) -> 5000 | S39: =I39+M39+P39 -> 1600 | U39: =S39*D39+R39+T39 -> 53000 | W39: =F39+U39 -> 88117.59 | AD39: =X39+Y39+Z39+AA39+AB39+#REF! -> #REF!
A40: 12 | B40: НК6 | C40: Захаров Андрей Юрьевич | D40: 31 | F40: 50000 | G40: 17212.65 | H40: =G40/$G$6 -> 0.92541129 | I40: =$N$7*IF(H40<93%,$O$7,IF(H40<95%,$P$7,IF(H40<98%,$Q$7,IF(H40<100%,$R$7,IF(H40>=100%,$S$7))))) -> 400 | J40: =2.93*2 -> 5.86 | K40: =4.06*2 -> 8.12 | L40: =K40/J40 -> 1.3856655 | M40: =$N$8*IF(L40>130%,$O$9,IF(L40>120%,$P$9,IF(L40>110%,$Q$9,IF(L40>100%,$R$9,IF(L40<=100%,S19))))) -> 400 | N40: 1.15 | O40: =N40/$F$6 -> 0.76666667 | P40: =$N$10*IF(O40<90%,$O$11,IF(O40<93%,$P$11,IF(O40<96%,$Q$11,IF(O40<100%,$R$11,IF(O40>=100%,$S$11))))) -> 400 | Q40: 0 | R40: =IF(Q40<1,0,IF(Q40<=3,$O$13,IF(Q40<=5,$P$13,IF(Q40<=7,$Q$13,IF(Q40<=10,$R$13,IF(Q40>10,$S$13)))))) -> 0 | S40: =I40+M40+P40 -> 1200 | U40: =S40*D40+R40+T40 -> 37200 | W40: =F40+U40+V40 -> 87200 | AD40: =X40+Y40+Z40+AA40+AB40+#REF! -> #REF!
B41: НК исп срок | C41: Веденяпин Сергей Юрьевич | F41: 37500 | U41: =F41 -> 37500 | W41: =F41+U41+V41 -> 75000
B42: НК исп срок | C42: Козлов Максим Юрьевич | F42: 15000 | U42: =F42 -> 15000 | W42: =F42+U42+V42 -> 30000
B43: НК исп срок | C43: Морозов Виктор Сергеевич | F43: 7963.89 | U43: =S43*D43+R43+T43 -> 0 | W43: =F43+U43+V43 -> 7963.89
D44: =SUM(D30:D43) -> 333 | E44: x | F44: =SUM(F30:F43)+F20+F21 -> 844872.88 | Q44: =SUM(Q30:Q43) -> 9 | R44: =SUM(R30:R43) -> 25000 | S44: x | U44: =SUM(U30:U43) -> 620700 | V44: =SUM(V30:V43) -> 0 | W44: =SUM(W30:W43) -> 1165572.9 | X44: =SUM(X30:X43) -> 0 | Y44: =SUM(Y30:Y43) -> 0 | Z44: =SUM(Z30:Z43) -> 0 | AA44: =SUM(AA30:AA43) -> 0 | AB44: =SUM(AB30:AB43) -> 0 | AD44: =X44+Y44+Z44+AA44+AB44+#REF! -> #REF!
W46: =R23+W44 -> 1615572.9 | X46: =X44+Y44+Z44+AA44+AB44+#REF! -> #REF!
B47: НОВАЯ СИСТЕМА МОТИВАЦИИ | G47: 569794 | H47: 280000
A48: № п/п | B48: Должность | C48: ФИО | D48: Оклад | G48: План по ВП | H48: Факт по ВП | I48: Перевыполнение плана по ВП | J48: План переменные расходы Д4 | K48: Факт по ТО иР | L48: Отклонения план-факт | M48: План по маржинальной прибыли | N48: ФАКТ по маржинальной прибыли | O48: % выполнения | AC48: ИТОГО ЗАРПЛАТА | AD48: Удержания | AE48: Премия к выплате
P49: План по прибыли | R49: Расход ДТ | X49: Доля МАП | AA49: Наличие премии в зависимости от перевыполнения плана по прибыли "0"-нет, "1"-да | AB49: ИТОГО ПРЕМИЯ
P50: Ставка при выполнении плана по МП | Q50: Премия за показатель | R50: План | S50: Факт | T50: Экономия/пережог | V50: Ставка при выполнении плана по МП и при наличии экономии | W50: Премия за показатель | X50: кол-во | Y50: Ставка при выполнении плана по МП | Z50: Премия за показатель
A52: 2 | B52: НК8 | C52: Николаев Игорь Евгеньевич | D52: 65 | E52: 2000 | F52: =D52*E52 -> 130000 | G52: =D52*$G$47 -> 37036610 | H52: 29827706 | I52: =H52-G52 -> -7208904.4 | J52: 11480756 | K52: 8337422.5 | L52: =J52-K52 -> 3143333.7 | M52: =G52-J52 -> 25555854 | N52: =H52-K52 -> 21490283 | O52: =N52/M52 -> 0.84091431 | P52: =IF(O52<100%,0,IF(O52<105%,1000,IF(O52<110%,1200,IF(O52<115%,1500,IF(O52>115%,2500))))) -> 0 | Q52: =D52*P52 -> 0 | R52: 32.42 | S52: 32.86 | T52: =R52-S52 -> -0.44 | U52: =S52/R52 -> 1.0135719 | V52: =IF(U52<=100%,600,IF(U52<=101%,500,IF(U52<=103%,400,IF(U52<=105%,300,IF(U52>105%,200)))))*AA52 -> 400 | W52: =D52*V52 -> 26000 | X52: =25/D52 -> 0.38461538 | Y52: =600*AA52 -> 600 | Z52: =D52*Y52 -> 39000 | AA52: 1 | AB52: =W52+Z52 -> 65000 | AC52: =F52+AB52 -> 195000 | AE52: =AB52-AD52 -> 65000
A53: 3 | B53: НК12 | C53: Попов Андрей Викторович | D53: 67 | E53: 2000 | F53: =D53*E53 -> 134000 | G53: =D53*$G$47 -> 38176198 | H53: 29642777 | I53: =H53-G53 -> -8533421 | J53: 10668680 | K53: 9590551.5 | L53: =J53-K53 -> 1078129 | M53: =G53-J53 -> 27507518 | N53: =H53-K53 -> 20052225 | O53: =N53/M53 -> 0.72897256 | P53: =IF(O53<100%,0,IF(O53<105%,1000,IF(O53<110%,1200,IF(O53<115%,1500,IF(O53>115%,2500))))) -> 0 | Q53: =D53*P53 -> 0 | R53: 32.29 | S53: 32.13 | T53: =R53-S53 -> 0.16 | U53: =S53/R53 -> 0.99504491 | V53: =IF(U53<=100%,600,IF(U53<=101%,500,IF(U53<=103%,400,IF(U53<=105%,300,IF(U53>105%,200)))))*AA53 -> 600 | W53: =D53*V53 -> 40200 | X53: =7/D53 -> 0.10447761 | Y53: 300 | Z53: =D53*Y53 -> 20100 | AA53: 1 | AB53: =W53+Z53 -> 60300 | AC53: =F53+AB53 -> 194300 | AE53: =AB53-AD53 -> 60300
A54: 4 | B54: НК13 | C54: Базыгутдинов Дамир | D54: 65 | E54: 2000 | F54: =D54*E54-14889.7 -> 115110.3 | G54: =D54*$G$47 -> 37036610 | H54: 28881133 | I54: =H54-G54 -> -8155477.1 | J54: 11051683 | K54: 10039922 | L54: =J54-K54 -> 1011760.7 | M54: =G54-J54 -> 25984927 | N54: =H54-K54 -> 18841211 | O54: =N54/M54 -> 0.7250823 | P54: =IF(O54<100%,0,IF(O54<105%,1000,IF(O54<110%,1200,IF(O54<115%,1500,IF(O54>115%,2500))))) -> 0 | Q54: =D54*P54 -> 0 | R54: 32.83 | S54: 33.44 | T54: =R54-S54 -> -0.61 | U54: =S54/R54 -> 1.0185806 | V54: =IF(U54<=100%,600,IF(U54<=101%,500,IF(U54<=103%,400,IF(U54<=105%,300,IF(U54>105%,200)))))*AA54 -> 400 | W54: =D54*V54 -> 26000 | X54: =26/D54 -> 0.4 | Y54: =600*AA54 -> 600 | Z54: =D54*Y54 -> 39000 | AA54: 1 | AB54: =W54+Z54 -> 65000 | AC54: =F54+AB54 -> 180110.3 | AE54: =AB54-AD54 -> 65000
A55: 5 | B55: НК4 | C55: Кочетов А.В. | D55: 70 | E55: 2000 | F55: =D55*E55 -> 140000 | G55: =D55*$G$47 -> 39885580 | H55: 36068629 | I55: =H55-G55 -> -3816950.9 | J55: 14482679 | K55: 11205596 | L55: =J55-K55 -> 3277082.6 | M55: =G55-J55 -> 25402901 | N55: =H55-K55 -> 24863033 | O55: =N55/M55 -> 0.97874777 | P55: =IF(O55<100%,0,IF(O55<105%,1000,IF(O55<110%,1200,IF(O55<115%,1500,IF(O55>115%,2500))))) -> 0 | Q55: =D55*P55 -> 0 | R55: 33.32 | S55: 33.39 | T55: =R55-S55 -> -0.07 | U55: =S55/R55 -> 1.0021008 | V55: =IF(U55<=100%,600,IF(U55<=101%,500,IF(U55<=103%,400,IF(U55<=105%,300,IF(U55>105%,200)))))*AA55 -> 500 | W55: =D55*V55 -> 35000 | X55: =34/D55 -> 0.48571429 | Y55: =600*AA55 -> 600 | Z55: =D55*Y55 -> 42000 | AA55: 1 | AB55: =W55+Z55 -> 77000 | AC55: =F55+AB55 -> 217000 | AE55: =AB55-AD55 -> 77000
A56: 6 | B56: НК5 | C56: Веденяпин Сергей Юрьевич | D56: 65 | E56: 2000 | F56: =D56*E56 -> 130000 | G56: =D56*$G$47-G47/30*120 -> 34757434 | H56: 29035617 | I56: =H56-G56 -> -5721817.3 | J56: 10637142 | K56: =15266022.71-K58 -> 10052454 | L56: =J56-K56 -> 584688.06 | M56: =G56-J56 -> 24120292 | N56: =H56-K56 -> 18983163 | O56: =N56/M56 -> 0.78702044 | P56: =IF(O56<100%,0,IF(O56<105%,1000,IF(O56<110%,1200,IF(O56<115%,1500,IF(O56>115%,2500))))) -> 0 | Q56: =D56*P56 -> 0 | R56: 32.25 | S56: 32.77 | T56: =R56-S56 -> -0.52 | U56: =S56/R56 -> 1.016124 | V56: =IF(U56<=100%,600,IF(U56<=101%,500,IF(U56<=103%,400,IF(U56<=105%,300,IF(U56>105%,200)))))*AA56 -> 400 | W56: =D56*V56 -> 26000 | X56: =17/D56 -> 0.26153846 | Y56: =600*AA56 -> 600 | Z56: =D56*Y56 -> 39000 | AA56: 1 | AB56: =W56+Z56 -> 65000 | AC56: =F56+AB56 -> 195000 | AE56: =AB56-AD56 -> 65000
A57: 8 | B57: НК6 | C57: Бикмуллин Айрат Равилевич | D57: 25 | E57: 0 | F57: =D57*E57 -> 0 | G57: =D57*H47 -> 7000000 | H57: 5710458.5 | I57: =H57-G57 -> -1289541.5 | J57: 1676603.6 | K57: 1064901.7 | L57: =J57-K57 -> 611701.96 | M57: =G57-J57 -> 5323396.4 | N57: =H57-K57 -> 4645556.8 | O57: =N57/M57 -> 0.87266785 | P57: =IF(O57<100%,0,IF(O57<105%,1000,IF(O57<110%,1200,IF(O57<115%,1500,IF(O57>115%,2500))))) -> 0 | Q57: =D57*P57 -> 0 | R57: 21.8 | S57: 21.37 | T57: =R57-S57 -> 0.43 | U57: =S57/R57 -> 0.98027523 | V57: =IF(U57<=100%,600,IF(U57<=101%,500,IF(U57<=103%,400,IF(U57<=105%,300,IF(U57>105%,200)))))*AA57 -> 0 | W57: =D57*V57 -> 0 | X57: =0/D57 -> 0 | Y57: 0 | Z57: =D57*Y57 -> 0 | AA57: 0 | AB57: =W57+Z57 -> 0 | AC57: =F57+AB57 -> 0 | AE57: =AB57-AD57 -> 0
G58: =D58*$G$47 -> 0 | K58: 5213569 | M58: =G58-J58 -> 0 | N58: =H58-K58 -> -5213569 | AC58: =F58+AB58 -> 0 | AE58: =AB58-AD58 -> 0
F59: =SUM(F52:F58) -> 649110.3 | G59: =SUM(G52:G57) -> 193892432 | H59: =SUM(H52:H58) -> 1.5916632e+08 | I59: =H59-G59 -> -34726112 | J59: =SUM(J52:J58) -> 59997543 | K59: =SUM(K52:K58) -> 55504416 | L59: =SUM(L52:L56) -> 9094994 | M59: =SUM(M52:M58) -> 1.3389489e+08 | N59: =SUM(N52:N58) -> 1.036619e+08 | AB59: =SUM(AB52:AB58) -> 332300 | AC59: =SUM(AC52:AC58) -> 981410.3 | AD59: =SUM(AD52:AD58) -> 0 | AE59: =AB59-AD59 -> 332300
D60: =SUM(D52:D59) -> 357 | E60: x | F60: =F59+F20+F21+F22 -> 1099110.3
AB61: =Q23+AB59 -> 332300 | AC61: =R23+AC59 -> 1431410.3

Sheet мех
B2: Механик-инженер
B4: Оклад | C4: 80000
B5: KPI за 1 ТС | C5: 1500
B8: Показатель KPI | C8: Вес | D8: На 1 ТС | E8: Коэффициенты
B9: КТГ | C9: 0.4 | D9: =C9*C5 -> 600 | E9: Менее 95% | F9: 95-95,99% | G9: 96-96,99% | H9: 97-97,99 | I9: 98% и более
E10: 0 | F10: 0.4 | G10: 0.6 | H10: 0.8 | I10: 1
B11: Выполнение плана по ремфонду | C11: 0.2 | D11: =C11*C5 -> 300 | E11: 110% и более | F11: 105-110% | G11: 100-105% | H11: 100% и менее
E12: 0 | F12: 0.6 | G12: 0.8 | H12: 1
E13: при 0,0 | F13: при 0,5 | G13: при 0,6 | H13: при 0,8 | I13: при 1,0
E14: 0 | F14: =F10*D9 -> 240 | G14: =G10*D9 -> 360 | H14: =H10*D9 -> 480 | I14: =I10*D9 -> 600
E15: 0 | F15: =F12*D11 -> 180 | G15: =G12*D11 -> 240 | H15: =H12*D11 -> 300 | I15: =D11*I12 -> 0
B16: Итого | E16: =E14+E15+C4 -> 80000 | F16: =F14+F15+C4 -> 80420 | G16: =G14+G15+C4 -> 80600 | H16: =H14+H15+C4 -> 80780 | I16: =I14+I15+C4 -> 80600
B17: Выполнение графика прохождения ТО и ИО | C17: 0.4 | D17: =C17*C5 -> 600 | E17: 0.95 | F17: 0.96 | G17: 0.97 | H17: 0.98 | I17: 1
E18: 0 | F18: 0.4 | G18: 0.6 | H18: 0.8 | I18: 1
B19: Испытательный период для новичков на 2 месяца: | C19: 100 000р
A22: Должность | B22: ФИО | C22: кол-во ТС | D22: Оклад | E22: Базовая премия | F22: КТГ | I22: Выполнение плана по ремфонду | N22: =B17 -> Выполнение графика прохождения ТО и ИО | R22: Итого премия | S22: ИТОГО ЗАРПЛАТА | T22: Удержания | U22: Премия к выплате
E23: ( 1300 руб. за каждое ТС) | F23: % выполнения | G23: Коэффициент | H23: Премия за показатель | I23: План | J23: Факт | K23: % выполнения | L23: Коэффициент | M23: Премия за показатель | N23: кол-во ТС факт | O23: % выполнения | P23: Коэффициент | Q23: Премия за показатель
A24: И-М | B24: Габитов Фаниль Фаргатович | C24: 93 | D24: ='Д4-ФОТ '!N19+'Д4-ФОТ '!S19 -> 80000 | E24: =C24*$C$5 -> 139500 | F24: 0.9914 | G24: =IF(F24<95%,$E$10,IF(F24<96%,$F$10,IF(F24<97%,G$10,IF(F24<98%,$H$10,IF(F24>=98%,$I$10))))) -> 1 | H24: =E24*$C$9*G24 -> 55800 | I24: 12728286 | J24: 11104824 | K24: =J24/I24 -> 0.87245238 | L24: =IF(K24>=110%,$E$12,IF(K24>=105%,$F$12,IF(K24>100%,$G$12,IF(K24<=100%,$H$12,)))) -> 1 | M24: =E24*$C$11*L24 -> 27900 | N24: =C24-8 -> 85 | O24: =N24/C24 -> 0.91397849 | P24: =IF(O24<$E$17,$E$18,IF(O24<$F$17,$F$18,IF(O24<$G$17,$G$18,IF(O24<$H$17,$H$18,IF(O24<=$I$17,$I$18))))) -> 0 | Q24: =E24*$C$17*P24 -> 0 | R24: =H24+M24+Q24 -> 83700 | S24: =D24+R24 -> 163700 | T24: =3*1000 -> 3000 | U24: =R24-T24 -> 80700
A25: И-М | B25: Кияметдинов Фарит Рустамович | C25: 67 | D25: ='Д4-ФОТ '!N23+'Д4-ФОТ '!S23 -> 80000 | E25: =C25*$C$5 -> 100500 | F25: 0.9856 | G25: =IF(F25<95%,$E$10,IF(F25<96%,$F$10,IF(F25<97%,G$10,IF(F25<98%,$H$10,IF(F25>=98%,$I$10))))) -> 1 | H25: =E25*$C$9*G25 -> 40200 | I25: =3023965.39+7644715.12 -> 10668681 | J25: =2526451.3+7064100.23 -> 9590551.5 | K25: =J25/I25 -> 0.89894449 | L25: =IF(K25>=110%,$E$12,IF(K25>=105%,$F$12,IF(K25>100%,$G$12,IF(K25<=100%,$H$12,)))) -> 1 | M25: =E25*$C$11*L25 -> 20100 | N25: =C25-2 -> 65 | O25: =N25/C25 -> 0.97014925 | P25: =IF(O25<$E$17,$E$18,IF(O25<$F$17,$F$18,IF(O25<$G$17,$G$18,IF(O25<$H$17,$H$18,IF(O25<=$I$17,$I$18))))) -> 0.8 | Q25: =E25*$C$17*P25 -> 32160 | R25: =H25+M25+Q25 -> 92460 | S25: =D25+R25 -> 172460 | T25: =5*1000 -> 5000 | U25: =R25-T25 -> 87460
A26: И-М | B26: Нурмухаметов Айрат Ринатович | C26: 65 | D26: ='Д4-ФОТ '!N26+'Д4-ФОТ '!S26 -> 80000 | E26: =C26*$C$5 -> 97500 | F26: 0.9898 | G26: =IF(F26<95%,$E$10,IF(F26<96%,$F$10,IF(F26<97%,G$10,IF(F26<98%,$H$10,IF(F26>=98%,$I$10))))) -> 1 | H26: =E26*$C$9*G26 -> 39000 | I26: 11181846 | J26: 8279192 | K26: =J26/I26 -> 0.74041369 | L26: =IF(K26>=110%,$E$12,IF(K26>=105%,$F$12,IF(K26>100%,$G$12,IF(K26<=100%,$H$12,)))) -> 1 | M26: =E26*$C$11*L26 -> 19500 | N26: =C26 -> 65 | O26: =N26/C26 -> 1 | P26: =IF(O26<$E$17,$E$18,IF(O26<$F$17,$F$18,IF(O26<$G$17,$G$18,IF(O26<$H$17,$H$18,IF(O26<=$I$17,$I$18))))) -> 1 | Q26: =E26*$C$17*P26 -> 39000 | R26: =H26+M26+Q26 -> 97500 | S26: =D26+R26 -> 177500 | U26: =R26-T26 -> 97500
A27: И-М | B27: Свистунов Дмитрий Петрович | C27: 137 | D27: ='Д4-ФОТ '!N28+'Д4-ФОТ '!S28 -> 80000 | E27: =C27*$C$5 -> 205500 | F27: 0.9874 | G27: =IF(F27<95%,$E$10,IF(F27<96%,$F$10,IF(F27<97%,G$10,IF(F27<98%,$H$10,IF(F27>=98%,$I$10))))) -> 1 | H27: =E27*$C$9*G27 -> 82200 | I27: 25119821 | J27: 26471619 | K27: =J27/I27 -> 1.053814 | L27: =IF(K27>=110%,$E$12,IF(K27>=105%,$F$12,IF(K27>100%,$G$12,IF(K27<=100%,$H$12,)))) -> 0.6 | M27: =E27*$C$11*L27 -> 24660 | N27: =C27-3 -> 134 | O27: =N27/C27 -> 0.97810219 | P27: =IF(O27<$E$17,$E$18,IF(O27<$F$17,$F$18,IF(O27<$G$17,$G$18,IF(O27<$H$17,$H$18,IF(O27<=$I$17,$I$18))))) -> 0.8 | Q27: =E27*$C$17*P27 -> 65760 | R27: =H27+M27+Q27 -> 172620 | S27: =D27+R27 -> 252620 | T27: =4*1000 -> 4000 | U27: =R27-T27 -> 168620
C28: =SUM(C24:C27) -> 362 | D28: =SUM(D24:D27) -> 320000 | E28: =SUM(E24:E27) -> 543000 | G28: x | H28: =SUM(H24:H27) -> 217200 | I28: =SUM(I24:I27) -> 59698634 | J28: =SUM(J24:J27) -> 55446186 | M28: =SUM(M24:M27) -> 92160 | Q28: =SUM(Q24:Q27) -> 136920 | R28: =SUM(R24:R27) -> 446280 | S28: =SUM(S24:S27) -> 766280 | T28: =SUM(T24:T27) -> 12000 | U28: =SUM(U24:U27) -> 434280 | V28: =SUM(V24:V27) -> 0

Sheet ФОТ Д4
A1: ТРАНСПОРТНАЯ КОМПАНИЯ
A2: Подразделение | C2: Оклад | F2: Премия (переменная часть) | G2: ИТОГО ФОТ | H2: Отраб.время | J2: Оф.з/п | O2: НДФЛ на оф. | P2: Аванс на карту | Q2: З/п на карту | R2: Остаток на начало расчетного периода | S2: Начислено по положению | V2: Отпускные | W2: Прочие доплаты | X2: Удержания | Y2: Итого начислено | Z2: К выплате через кассу | AA2: Выплачено через кассу | AC2: Остаток на конец расчетного периода | AD2: примечание
A3: Должность | B3: Сотрудник | C3: Офиц | D3: Неофиц | E3: ОКЛАД Всего | H3: План | I3: Факт | J3: Оклад | K3: Премия | L3: Отпускные | M3: Комп. при увольнении по соглашению сторон | N3: Итого | S3: Оклад | T3: Премия | U3: Итого
A4: Д4-Производственный департамент | C4: =C5+C7+C20+C38+C47 -> 928344 | D4: =D5+D7+D20+D38+D47 -> 2395406 | E4: =E5+E7+E20+E38+E47 -> 3323750 | F4: =F5+F7+F20+F38+F47 -> 495000.03 | G4: =G5+G7+G20+G38+G47 -> 3818750 | H4: =H5+H7+H20+H38+H47 -> 897 | I4: =I5+I7+I20+I38+I47 -> 800 | J4: =J5+J7+J20+J38+J47 -> 742079.82 | ... AC4: =AC5+AC7+AC20+AC38+AC47 -> #REF!
B5: РД4 | C5: =SUM(C6:C6) -> 26250 | D5: =SUM(D6:D6) -> 273750 | E5: =SUM(E6:E6) -> 300000 | F5: =SUM(F6:F6) -> 0.03 | G5: =SUM(G6:G6) -> 300000.03 | H5: =SUM(H6:H6) -> 23 | I5: =SUM(I6:I6) -> 23 | J5: =SUM(J6:J6) -> 26250 | ... AC5: =SUM(AC6:AC6) -> 0
A6: РД4 | B6: Аматыч Роберт Альбертович | C6: 26250 | D6: 273750 | E6: =C6+D6 -> 300000 | F6: 0.03 | G6: =E6+F6 -> 300000.03 | H6: 23 | I6: 23 | J6: 26250 | K6: 5250 | N6: =J6+K6+L6+M6 -> 31500 | O6: 3913 | P6: 10922.35 | Q6: =N6-O6-P6 -> 16664.65 | R6: =[1]июнь24!AC60 -> 0 | S6: =D6/H6*I6-K6 -> 268500 | T6: 0 | U6: =T6+S6 -> 268500 | Y6: =N6+U6+V6+W6 -> 300000 | Z6: =Y6-O6-P6-Q6-X6 -> 268500 | AA6: 268500 | AB6: 0 | AC6: =R6+Z6-AA6-AB6 -> 0
B7: Производственный отдел | C7: =SUM(C8:C19) -> 291900 | D7: =SUM(D8:D19) -> 1008100 | E7: =SUM(E8:E19) -> 1300000 | F7: =SUM(F8:F19) -> 0 | G7: =SUM(G8:G19) -> 1300000 | H7: =SUM(H8:H19) -> 276 | I7: =SUM(I8:I19) -> 250 | J7: =SUM(J8:J19) -> 228900 | ... AC7: =SUM(AC8:AC19) -> #REF!
A8: НК | B8: Базыгутдинов Дамир Асафутинович | C8: 26250 | D8: 73750 | E8: =C8+D8 -> 100000 | G8: =E8+F8 -> 100000 | H8: 23 | I8: 23 | J8: 26250 | K8: 5250 | N8: =J8+K8+L8+M8 -> 31500 | O8: 3848 | P8: 10922.35 | Q8: =N8-O8-P8 -> 16729.65 | R8: =[1]июнь24!AC63 -> 8.4711765 | S8: =43*2000-J8-K8 -> 54500 | T8: ='НК, РГ'!AB54 -> 65000 | U8: =T8+S8 -> 119500 | Y8: =N8+U8+V8+W8 -> 151000 | Z8: =Y8-O8-P8-Q8-X8 -> 119500 | AA8: 56500 | AC8: =R8+Z8-AA8-AB8 -> 63008.471
A9: НК | B9: Веденяпин Сергей Юрьевич | C9: 26250 | D9: 73750 | E9: =C9+D9 -> 100000 | F9: 0 | G9: =E9+F9 -> 100000 | H9: 23 | I9: 23 | J9: 26250 | K9: 5250 | N9: =J9+K9+L9+M9 -> 31500 | O9: 4095 | P9: 10922.35 | Q9: =N9-O9-P9 -> 16482.65 | R9: =[1]июнь24!AC64 -> 75 | S9: =31*2000-J9-K9 -> 30500 | T9: ='НК, РГ'!AB56 -> 65000 | U9: =T9+S9 -> 95500 | X9: =352-352 -> 0 | Y9: =N9+U9+V9+W9 -> 127000 | Z9: =Y9-O9-P9-Q9-X9 -> 95500 | AA9: 30500 | AC9: =R9+Z9-AA9-AB9 -> 65075
A10: НК | B10: Захаров Андрей Юрьевич | C10: 26250 | D10: 73750 | E10: =C10+D10 -> 100000 | G10: =E10+F10 -> 100000 | H10: 23 | I10: 10 | J10: 11413.04 | K10: 0 | L10: 22551.48 | N10: =J10+K10+L10+M10 -> 33964.52 | O10: =4416+5909.71 -> 10325.71 | P10: 23638.81 | Q10: =N10-O10-P10 -> 0 | R10: =[1]июнь24!AC65 -> 13.34 | S10: =32*2000/23*10-J10 -> 16413.047 | T10: 0 | U10: =T10+S10 -> 16413.047 | Y10: =N10+U10+V10+W10 -> 50377.567 | Z10: =Y10-O10-P10-Q10-X10 -> 16413.047 | AA10: 16400 | AC10: =R10+Z10-AA10-AB10 -> 26.386957
A11: НК | B11: Зыков Андрей Юрьевич | C11: 26250 | D11: 73750 | E11: =C11+D11 -> 100000 | G11: =E11+F11 -> 100000 | H11: 23 | I11: 10 | J11: 11413.04 | K11: 0 | L11: 17333.15 | N11: =J11+K11+L11+M11 -> 28746.19 | O11: =3737+6252.3 -> 9989.3 | P11: 18756.89 | Q11: =N11-O11-P11 -> 0 | R11: =[1]июнь24!AC66 -> 92.48 | S11: =33*2000/23*10-J11 -> 17282.612 | T11: 0 | U11: =T11+S11 -> 17282.612 | Y11: =N11+U11+V11+W11 -> 46028.802 | Z11: =Y11-O11-P11-Q11-X11 -> 17282.612 | AA11: 17300 | AC11: =R11+Z11-AA11-AB11 -> 75.092174
A12: НК | B12: Козлов Максим Юрьевич | C12: 26250 | D12: 73750 | E12: =C12+D12 -> 100000 | F12: 0 | G12: =E12+F12 -> 100000 | H12: 23 | I12: 23 | J12: 26250 | K12: 5250 | N12: =J12+K12+L12+M12 -> 31500 | O12: 4095 | P12: 10922.35 | Q12: =N12-O12-P12 -> 16482.65 | R12: =[1]июнь24!AC67 -> 50 | T12: ='НК, РГ'!#REF! -> #REF! | U12: =T12+S12 -> #REF! | X12: =1457-1457 -> 0 | Y12: =N12+U12+V12+W12 -> #REF! | Z12: =Y12-O12-P12-Q12-X12 -> #REF! | AC12: =R12+Z12-AA12-AB12 -> #REF!
A13: НК | B13: Кочетов Александр Валерьевич | C13: 26250 | D13: 73750 | E13: =C13+D13 -> 100000 | G13: =E13+F13 -> 100000 | H13: 23 | I13: 23 | J13: 26250 | K13: 5250 | N13: =J13+K13+L13+M13 -> 31500 | O13: 3913 | P13: 10922.35 | Q13: =N13-O13-P13 -> 16664.65 | R13: =[1]июнь24!AC68 -> 0 | S13: =67*2000-J13-K13 -> 102500 | T13: ='НК, РГ'!AB55 -> 77000 | U13: =T13+S13 -> 179500 | X13: 1850 | Y13: =N13+U13+V13+W13 -> 211000 | Z13: =Y13-O13-P13-Q13-X13 -> 177650 | AA13: 102500 | AC13: =R13+Z13-AA13-AB13 -> 75150
A14: РГ | B14: Мулындин Денис Михайлович | D14: 150000 | E14: =C14+D14 -> 150000 | G14: =E14+F14 -> 150000 | H14: 23 | I14: 23 | N14: =J14+K14+L14+M14 -> 0 | Q14: =N14-O14-P14 -> 0 | R14: =[1]июнь24!AC69 -> 49.166667 | S14: =D14/H14*I14-K14 -> 150000 | T14: ='НК, РГ'!P20 -> 0 | U14: =T14+S14 -> 150000 | X14: =140105/6+650 -> 24000.833 | Y14: =N14+U14+V14+W14 -> 150000 | Z14: =Y14-O14-P14-Q14-X14 -> 125999.17 | AA14: =25000+101000 -> 126000 | AC14: =R14+Z14-AA14-AB14 -> 48.333333
A15: НК | B15: Набиуллин Фидус Фанзильевич | C15: 26250 | D15: 73750 | E15: =C15+D15 -> 100000 | G15: =E15+F15 -> 100000 | H15: 23 | I15: 23 | J15: 26250 | K15: 5250 | N15: =J15+K15+L15+M15 -> 31500 | O15: 3913 | P15: 10922.35 | Q15: =N15-O15-P15 -> 16664.65 | R15: =[1]июнь24!AC70 -> 84 | S15: =42*2000-J15-K15 -> 52500 | T15: ='НК, РГ'!AB52 -> 65000 | U15: =T15+S15 -> 117500 | X15: 988 | Y15: =N15+U15+V15+W15 -> 149000 | Z15: =Y15-O15-P15-Q15-X15 -> 116512 | AA15: 51500 | AC15: =R15+Z15-AA15-AB15 -> 65096
A16: НК | B16: Пахулин Андрей Михайлович | C16: 26250 | D16: 73750 | E16: =C16+D16 -> 100000 | G16: =E16+F16 -> 100000 | H16: 23 | I16: 23 | J16: 14836.96 | K16: 2967.39 | L16: 15024.38 | N16: =J16+K16+L16+M16 -> 32828.73 | O16: 4267 | P16: =4964.52+13071.38 -> 18035.9 | Q16: =N16-O16-P16 -> 10525.83 | R16: =[1]июнь24!AC71 -> 69 | S16: =30*2000-J16-K16-L16 -> 27171.27 | T16: ='НК, РГ'!#REF! -> #REF! | U16: =T16+S16 -> #REF! | Y16: =N16+U16+V16+W16 -> #REF! | Z16: =Y16-O16-P16-Q16-X16 -> #REF! | AA16: =7200+20000 -> 27200 | AC16: =R16+Z16-AA16-AB16 -> #REF!
A17: НК | B17: Попов Андрей Викторович | C17: 26250 | D17: 73750 | E17: =C17+D17 -> 100000 | G17: =E17+F17 -> 100000 | H17: 23 | I17: 23 | J17: 17119.57 | K17: 3423.91 | L17: 14404.74 | N17: =J17+K17+L17+M17 -> 34948.22 | O17: 4544 | P17: =10922.35+12531.74 -> 23454.09 | Q17: =N17-O17-P17 -> 6950.13 | R17: =[1]июнь24!AC72 -> 31.997059 | S17: =52*2000-J17-K17-L17 -> 69051.78 | T17: ='НК, РГ'!AB53 -> 60300 | U17: =T17+S17 -> 129351.78 | Y17: =N17+U17+V17+W17 -> 164300 | Z17: =Y17-O17-P17-Q17-X17 -> 129351.78 | AA17: 69000 | AC17: =R17+Z17-AA17-AB17 -> 60383.777
A18: РГ | B18: Рашитов Рамиль Камилович | C18: 29400 | D18: =E18-C18 -> 120600 | E18: 150000 | G18: =E18+F18 -> 150000 | H18: 23 | I18: 23 | J18: 16617.39 | K18: 3323.48 | L18: 16764.16 | N18: =J18+K18+L18+M18 -> 36705.03 | O18: 4589 | P18: =11120.61+14585.16 -> 25705.77 | Q18: =N18-O18-P18 -> 6410.26 | R18: =[1]июнь24!AC73 -> 79559 | S18: =D18/H18*I18-K18-3981.55 -> 113294.97 | T18: ='НК, РГ'!P21 -> 0 | U18: =T18+S18 -> 113294.97 | Y18: =N18+U18+V18+W18 -> 150000 | Z18: =Y18-O18-P18-Q18-X18 -> 113294.97 | AA18: 192800 | AC18: =R18+Z18-AA18-AB18 -> 53.97
A19: НК | B19: Федоров Евгений Александрович | C19: 26250 | D19: 73750 | E19: =C19+D19 -> 100000 | F19: 0 | G19: =E19+F19 -> 100000 | H19: 23 | I19: 23 | J19: 26250 | K19: 5250 | N19: =J19+K19+L19+M19 -> 31500 | O19: 4095 | P19: 10922.35 | Q19: =N19-O19-P19 -> 16482.65 | R19: =[1]июнь24!AC74 -> 50 | S19: =38*2000-J19-K19 -> 44500 | T19: ='НК, РГ'!#REF! -> #REF! | U19: =T19+S19 -> #REF! | Y19: =N19+U19+V19+W19 -> #REF! | Z19: =Y19-O19-P19-Q19-X19 -> #REF! | AA19: 44500 | AC19: =R19+Z19-AA19-AB19 -> #REF!
B20: Технический отдел | C20: =SUM(C21:C37) -> 430200 | D20: =SUM(D21:D37) -> 869800 | E20: =SUM(E21:E37) -> 1300000 | F20: =SUM(F21:F37) -> 370000 | G20: =SUM(G21:G37) -> 1670000 | H20: =SUM(H21:H37) -> 391 | I20: =SUM(I21:I37) -> 343 | J20: =SUM(J21:J37) -> 357186.22 | ... AC20: =SUM(AC21:AC37) -> 309939.36
A21: Механик - контролер | B21: Асулханов Айрат Анварович | C21: 23630 | D21: 21370 | E21: =C21+D21 -> 45000 | F21: 30000 | G21: =E21+F21 -> 75000 | H21: 23 | I21: 11 | J21: =17328.67+1906.62 -> 19235.29 | K21: 3465.73 | N21: =J21+K21+L21+M21 -> 22701.02 | O21: 2951 | P21: 4111 | Q21: =N21-O21-P21 -> 15639.02 | R21: =[1]июнь24!AC76 -> -20.63 | S21: =D21/H21*I21-K21 -> 6754.7048 | T21: =F21/H21*I21 -> 14347.826 | U21: =T21+S21 -> 21102.531 | Y21: =N21+U21+V21+W21 -> 43803.551 | Z21: =Y21-O21-P21-Q21-X21 -> 21102.531 | AA21: 6700 | AC21: =R21+Z21-AA21-AB21 -> 14381.901
A22: Инженер-механик | B22: Габдракипов Нафис Фанисович | C22: 26250 | D22: 73750 | E22: =C22+D22 -> 100000 | F22: 0 | G22: =E22+F22 -> 100000 | H22: 23 | I22: 13 | J22: 14836.96 | K22: 2967.39 | N22: =J22+K22+L22+M22 -> 17804.35 | O22: 2315 | P22: 993.3 | Q22: =N22-O22-P22 -> 14496.05 | R22: 0 | S22: =D22/H22*I22-K22 -> 38717.393 | T22: =F22/H22*I22 -> 0 | U22: =T22+S22 -> 38717.393 | Y22: =N22+U22+V22+W22 -> 56521.743 | Z22: =Y22-O22-P22-Q22-X22 -> 38717.393 | AA22: 38700 | AC22: =R22+Z22-AA22-AB22 -> 17.392609
A23: Механик - контролер | B23: Галимов Ильнур Ирикович | C23: 23630 | D23: 21370 | E23: =C23+D23 -> 45000 | F23: 30000 | G23: =E23+F23 -> 75000 | H23: 23 | I23: 23 | J23: 14768.75 | K23: 2953.75 | N23: =J23+K23+L23+M23 -> 17722.5 | O23: 1940 | P23: 2569.75 | Q23: =N23-O23-P23 -> 13212.75 | R23: =[1]июнь24!AC77 -> 3.7370588 | S23: =D23/H23*I23-K23-2153.61 -> 16262.64 | T23: =F23/H23*I23 -> 30000 | U23: =T23+S23 -> 46262.64 | Y23: =N23+U23+V23+W23 -> 63985.14 | Z23: =Y23-O23-P23-Q23-X23 -> 46262.64 | AA23: 16200 | AC23: =R23+Z23-AA23-AB23 -> 30066.377
A24: Инженер-механик | B24: Габитов Фаниль Фаргатович | C24: 26250 | D24: 73750 | E24: =C24+D24 -> 100000 | F24: 0 | G24: =E24+F24 -> 100000 | H24: 23 | I24: 23 | J24: 26250 | K24: 5250 | N24: =J24+K24+L24+M24 -> 31500 | O24: 4095 | P24: =10922.35 -> 10922.35 | Q24: =N24-O24-P24 -> 16482.65 | R24: =[1]июнь24!AC78 -> 78.944211 | S24: =D24/H24*I24-K24 -> 68500 | T24: =F24/H24*I24 -> 0 | U24: =T24+S24 -> 68500 | Y24: =N24+U24+V24+W24 -> 100000 | Z24: =Y24-O24-P24-Q24-X24 -> 68500 | AA24: 68500 | AC24: =R24+Z24-AA24-AB24 -> 78.944211
A25: ведущий механик | B25: Дресвянников Виктор Владимирович | C25: 26250 | D25: 123750 | E25: =C25+D25 -> 150000 | G25: =E25+F25 -> 150000 | H25: 23 | I25: 23 | J25: 26250 | K25: 5250 | N25: =J25+K25+L25+M25 -> 31500 | O25: 4095 | P25: 10921.35 | Q25: =N25-O25-P25 -> 16483.65 | R25: =[1]июнь24!AC79 -> 63.162105 | S25: =D25/H25*I25-K25 -> 118500 | T25: =F25/H25*I25 -> 0 | U25: =T25+S25 -> 118500 | Y25: =N25+U25+V25+W25 -> 150000 | Z25: =Y25-O25-P25-Q25-X25 -> 118500 | AA25: 118500 | AC25: =R25+Z25-AA25-AB25 -> 63.162105
A26: Инженер-механик | B26: Кияметдинов Фарит Рустамович | C26: 26250 | D26: 73750 | E26: =C26+D26 -> 100000 | F26: 0 | G26: =E26+F26 -> 100000 | H26: 23 | I26: 23 | J26: 26250 | K26: 5250 | N26: =J26+K26+L26+M26 -> 31500 | O26: 4095 | P26: 10922.35 | Q26: =N26-O26-P26 -> 16482.65 | R26: =[1]июнь24!AC80 -> 50 | S26: =D26/H26*I26-K26 -> 68500 | T26: =F26/H26*I26 -> 0 | U26: =T26+S26 -> 68500 | Y26: =N26+U26+V26+W26 -> 100000 | Z26: =Y26-O26-P26-Q26-X26 -> 68500 | AA26: 68500 | AC26: =R26+Z26-AA26-AB26 -> 50
A27: Главный механик | B27: Кузьмин Алексей Викторович | C27: 29400 | D27: 80600 | E27: =C27+D27 -> 110000 | F27: 90000 | G27: =E27+F27 -> 200000 | H27: 23 | I27: 22 | J27: 28121.74 | K27: 5624.35 | N27: =J27+K27+L27+M27 -> 33746.09 | O27: 4387 | P27: 12232.87 | Q27: =N27-O27-P27 -> 17126.22 | R27: =[1]июнь24!AC81 -> 27.79 | S27: =D27/H27*I27-K27 -> 71471.302 | T27: =F27/H27*I27 -> 86086.957 | U27: =T27+S27 -> 157558.26 | Y27: =N27+U27+V27+W27 -> 191304.35 | Z27: =Y27-O27-P27-Q27-X27 -> 157558.26 | AA27: 71400 | AC27: =R27+Z27-AA27-AB27 -> 86186.049
A28: Инженер-механик | B28: Мифтахов Ильдар Зуфарович | C28: 26250 | D28: 73750 | E28: =C28+D28 -> 100000 | F28: 0 | G28: =E28+F28 -> 100000 | H28: 23 | I28: 23 | J28: 26250 | K28: 5250 | N28: =J28+K28+L28+M28 -> 31500 | O28: 4095 | P28: 10922.35 | Q28: =N28-O28-P28 -> 16482.65 | R28: =[1]июнь24!AC82 -> 0 | S28: =D28/H28*I28-K28 -> 68500 | T28: =F28/H28*I28 -> 0 | U28: =T28+S28 -> 68500 | Y28: =N28+U28+V28+W28 -> 100000 | Z28: =Y28-O28-P28-Q28-X28 -> 68500 | AA28: 68500 | AC28: =R28+Z28-AA28-AB28 -> 0
A29: Механик по обслуживанию транспортных средств | B29: Набиев Рустам Нариманович | C29: 26250 | D29: 73750 | E29: =C29+D29 -> 100000 | G29: =E29+F29 -> 100000 | H29: 23 | I29: 23 | J29: 17119.57 | K29: 3423.91 | L29: 14687.54 | N29: =J29+K29+L29+M29 -> 35231.02 | O29: =4580+7662.76 -> 12242.76 | P29: =8191.76+9583.9 -> 17775.66 | Q29: =N29-O29-P29 -> 5212.6 | R29: =[1]июнь24!AC83 -> 42.645294 | S29: =D29/H29*I29-K29-5557.11 -> 64768.98 | T29: =F29/H29*I29 -> 0 | U29: =T29+S29 -> 64768.98 | Y29: =N29+U29+V29+W29 -> 100000 | Z29: =Y29-O29-P29-Q29-X29 -> 64768.98 | AA29: 64800 | AC29: =R29+Z29-AA29-AB29 -> 11.625294
A30: Инженер-механик | B30: Николаев Игорь Евгеньевич | C30: 26250 | D30: 73750 | E30: =C30+D30 -> 100000 | F30: 0 | G30: =E30+F30 -> 100000 | H30: 23 | I30: 21 | J30: 23967.39 | K30: 4793.48 | N30: =J30+K30+L30+M30 -> 28760.87 | O30: 3739 | P30: 8936.74 | Q30: =N30-O30-P30 -> 16085.13 | R30: 0 | S30: =D30/H30*I30-K30-5557.11 -> 56986.367 | T30: =F30/H30*I30 -> 0 | U30: =T30+S30 -> 56986.367 | Y30: =N30+U30+V30+W30 -> 85747.237 | Z30: =Y30-O30-P30-Q30-X30 -> 56986.367 | AA30: 56900 | AC30: =R30+Z30-AA30-AB30 -> 86.366522
A31: Старший механик - контролер | B31: Сафуанов Амир Мансурович | C31: 26250 | D31: =E31-C31 -> 23750 | E31: 50000 | F31: 40000 | G31: =E31+F31 -> 90000 | H31: 23 | I31: 23 | J31: 26250 | K31: 5250 | N31: =J31+K31+L31+M31 -> 31500 | O31: 4095 | P31: 10922.35 | Q31: =N31-O31-P31 -> 16482.65 | R31: =[1]июнь24!AC84 -> 2.98 | S31: =D31/H31*I31-K31 -> 18500 | T31: =F31/H31*I31 -> 40000 | U31: =T31+S31 -> 58500 | Y31: =N31+U31+V31+W31 -> 90000 | Z31: =Y31-O31-P31-Q31-X31 -> 58500 | AA31: 18500 | AC31: =R31+Z31-AA31-AB31 -> 40002.98
A32: Инженер-механик | B32: Свистунов Дмитрий Петрович | C32: 26250 | D32: 73750 | E32: =C32+D32 -> 100000 | F32: 0 | G32: =E32+F32 -> 100000 | H32: 23 | I32: 23 | J32: 26250 | K32: 5250 | N32: =J32+K32+L32+M32 -> 31500 | O32: 4095 | P32: 10922.35 | Q32: =N32-O32-P32 -> 16482.65 | R32: 0 | S32: =D32/H32*I32-K32 -> 68500 | T32: =F32/H32*I32 -> 0 | U32: =T32+S32 -> 68500 | Y32: =N32+U32+V32+W32 -> 100000 | Z32: =Y32-O32-P32-Q32-X32 -> 68500 | AA32: 68500 | AC32: =R32+Z32-AA32-AB32 -> 0
A33: Механик - контролер | B33: Скобяк Дмитрий Владиславович | C33: 23630 | D33: 21370 | E33: =C33+D33 -> 45000 | F33: 30000 | G33: =E33+F33 -> 75000 | H33: 23 | I33: 22 | J33: 22602.61 | K33: 4520.52 | N33: =J33+K33+L33+M33 -> 27123.13 | O33: 3526 | P33: 9832.3 | Q33: =N33-O33-P33 -> 13764.83 | R33: =[1]июнь24!AC85 -> 87.255789 | S33: =D33/H33*I33-K33 -> 15920.35 | T33: =F33/H33*I33 -> 28695.652 | U33: =T33+S33 -> 44616.002 | Y33: =N33+U33+V33+W33 -> 71739.132 | Z33: =Y33-O33-P33-Q33-X33 -> 44616.002 | AA33: 15900 | AC33: =R33+Z33-AA33-AB33 -> 28803.258
A34: Механик - контролер | B34: Спиридонов Алик Альбертович | C34: 23630 | D34: 21370 | E34: =C34+D34 -> 45000 | F34: 30000 | G34: =E34+F34 -> 75000 | H34: 23 | I34: 23 | J34: 23630 | K34: 4726 | N34: =J34+K34+L34+M34 -> 28356 | O34: 678 | P34: 10851.3 | Q34: =N34-O34-P34 -> 16826.7 | R34: =[1]июнь24!AC86 -> 74.741053 | S34: =D34/H34*I34-K34 -> 16644 | T34: =F34/H34*I34 -> 30000 | U34: =T34+S34 -> 46644 | Y34: =N34+U34+V34+W34 -> 75000 | Z34: =Y34-O34-P34-Q34-X34 -> 46644 | AA34: 16700 | AC34: =R34+Z34-AA34-AB34 -> 30018.741
A35: Инженер механик | B35: Тагиров Искандер Маратович | C35: 26250 | D35: =E35-C35 -> 13750 | E35: 40000 | F35: 40000 | G35: =E35+F35 -> 80000 | H35: 23 | I35: 1 | J35: 1141.3 | L35: 11598.93 | N35: =J35+K35+L35+M35 -> 12740.23 | O35: 1657 | P35: 11083.23 | Q35: =N35-O35-P35 -> 0 | R35: =[1]июнь24!AC87 -> 30.17 | S35: =D35/H35*I35-K35 -> 597.82609 | T35: =F35/H35*I35 -> 1739.1304 | U35: =T35+S35 -> 2336.9565 | Y35: =N35+U35+V35+W35 -> 15077.187 | Z35: =Y35-O35-P35-Q35-X35 -> 2336.9565 | AA35: 2300 | AC35: =R35+Z35-AA35-AB35 -> 67.126522
A36: специалист по технической документации | B36: Фалахова Алсу Халиловна | C36: 21890 | D36: 13110 | E36: =C36+D36 -> 35000 | F36: 40000 | G36: =E36+F36 -> 75000 | H36: 23 | I36: 23 | J36: 12372.61 | K36: 2474.52 | L36: 12440.54 | N36: =J36+K36+L36+M36 -> 27287.67 | O36: 3366 | P36: =9108.13+10822.54 -> 19930.67 | Q36: =N36-O36-P36 -> 3991 | R36: =[1]июнь24!AC88 -> 71.11 | S36: =D36/H36*I36-K36-2923.15 -> 7712.33 | T36: =F36/H36*I36 -> 40000 | U36: =T36+S36 -> 47712.33 | Y36: =N36+U36+V36+W36 -> 75000 | Z36: =Y36-O36-P36-Q36-X36 -> 47712.33 | AA36: 7700 | AC36: =R36+Z36-AA36-AB36 -> 40083.44
A37: специалист по технической документации | B37: Хайруллина Екатерина Сергеевна | C37: 21890 | D37: 13110 | E37: =C37+D37 -> 35000 | F37: 40000 | G37: =E37+F37 -> 75000 | H37: 23 | I37: 23 | J37: 21890 | K37: 4378 | N37: =J37+K37+L37+M37 -> 26268 | O37: 3051 | P37: 9108.13 | Q37: =N37-O37-P37 -> 14108.87 | R37: =[1]июнь24!AC89 -> -10 | S37: =D37/H37*I37-K37 -> 8732 | T37: =F37/H37*I37 -> 40000 | U37: =T37+S37 -> 48732 | Y37: =N37+U37+V37+W37 -> 75000 | Z37: =Y37-O37-P37-Q37-X37 -> 48732 | AA37: 8700 | AC37: =R37+Z37-AA37-AB37 -> 40022
B38: Отдел сопровождения водителей | C38: =SUM(C39:C46) -> 153744 | D38: =SUM(D39:D46) -> 120006 | E38: =SUM(E39:E46) -> 273750 | F38: =SUM(F39:F46) -> 125000 | G38: =SUM(G39:G46) -> 398750 | H38: =SUM(H39:H46) -> 184 | I38: =SUM(I39:I46) -> 161 | J38: =SUM(J39:J46) -> 103493.6 | ... AC38: =SUM(AC39:AC46) -> 125286.46
A39: Оператор | B39: Борейко Оксана Ивановна | C39: 21890 | D39: =E39-C39 -> 18110 | E39: 40000 | F39: 10000 | G39: =E39+F39 -> 50000 | H39: 23 | I39: 23 | J39: 9517.39 | K39: 1903.48 | L39: 19101.81 | N39: =J39+K39+L39+M39 -> 30522.68 | O39: 3968 | P39: =8280.39+16618.81 -> 24899.2 | Q39: =N39-O39-P39 -> 1655.48 | R39: =[1]июнь24!AC91 -> 36.15 | S39: =D39/H39*I39-K39-6729.2 -> 9477.32 | T39: =F39/H39*I39 -> 10000 | U39: =T39+S39 -> 19477.32 | Y39: =N39+U39+V39+W39 -> 50000 | Z39: =Y39-O39-P39-Q39-X39 -> 19477.32 | AA39: 9500 | AC39: =R39+Z39-AA39-AB39 -> 10013.47
B40: Ерошкина Виктория Константиновна | H40: 23 | N40: =J40+K40+L40+M40 -> 0 | Q40: =N40-O40-P40 -> 0 | R40: =[1]июнь24!AC92 -> 0 | S40: =D40/H40*I40-K40 -> 0 | U40: =T40+S40 -> 0 | Y40: =N40+U40+V40+W40 -> 0 | Z40: =Y40-O40-P40-Q40-X40 -> 0 | AA40: 0 | AC40: =R40+Z40-AA40-AB40 -> 0
A41: Оператор | B41: Ковалева Юлия Сергеевна | C41: 21890 | D41: =E41-C41 -> 21860 | E41: =40000+3750 -> 43750 | F41: 10000 | G41: =E41+F41 -> 53750 | H41: 23 | I41: 23 | J41: 12372.61 | K41: 2474.52 | N41: =J41+K41+L41+M41 -> 14847.13 | O41: 1930 | P41: 827.74 | Q41: =N41-O41-P41 -> 12089.39 | R41: =[1]июнь24!AC93 -> 92.003529 | S41: =D41/H41*I41-K41-3389.07 -> 15996.41 | T41: =F41/H41*I41 -> 10000 | U41: =T41+S41 -> 25996.41 | Y41: =N41+U41+V41+W41 -> 40843.54 | Z41: =Y41-O41-P41-Q41-X41 -> 25996.41 | AA41: 16000 | AC41: =R41+Z41-AA41-AB41 -> 10088.414
A42: Водитель-курьер | B42: Костин Сергей Васильевич | C42: 22402 | D42: =E42-C42 -> 7598 | E42: 30000 | F42: 60000 | G42: =E42+F42 -> 90000 | H42: 23 | I42: 23 | J42: =11010.43+1651.56 -> 12661.99 | K42: 2202.09 | N42: =J42+K42+L42+M42 -> 14864.08 | O42: 1361 | P42: 847 | Q42: =N42-O42-P42 -> 12656.08 | R42: =[1]июнь24!AC94 -> 93.04 | S42: =D42/H42*I42-K42-2714.25 -> 2681.66 | T42: =F42/H42*I42 -> 60000 | U42: =T42+S42 -> 62681.66 | Y42: =N42+U42+V42+W42 -> 77545.74 | Z42: =Y42-O42-P42-Q42-X42 -> 62681.66 | AA42: 2700 | AC42: =R42+Z42-AA42-AB42 -> 60074.7
A43: Оператор | B43: Костина Рузиля Равилевна | C43: 21890 | D43: =E43-C43 -> 18110 | E43: 40000 | F43: 10000 | G43: =E43+F43 -> 50000 | H43: 23 | I43: 23 | J43: 11753.98 | K43: 2350.8 | N43: =J43+K43+L43+M43 -> 14104.78 | O43: 1470 | P43: 1190.13 | Q43: =N43-O43-P43 -> 11444.65 | R43: =[1]июнь24!AC95 -> 23.86 | S43: =D43/H43*I43-K43-1725.48 -> 14033.72 | T43: =F43/H43*I43 -> 10000 | U43: =T43+S43 -> 24033.72 | Y43: =N43+U43+V43+W43 -> 38138.5 | Z43: =Y43-O43-P43-Q43-X43 -> 24033.72 | AA43: 14000 | AC43: =R43+Z43-AA43-AB43 -> 10057.58
A44: Оператор | B44: Кузьмина Гузель Назиповна | C44: 21891 | D44: =E44-C44 -> 18109 | E44: 40000 | F44: 10000 | G44: =E44+F44 -> 50000 | H44: 23 | I44: 23 | J44: 17512 | K44: 3502.4 | L44: 6456.24 | N44: =J44+K44+L44+M44 -> 27470.64 | O44: 3571 | P44: =8887.33+5617.24 -> 14504.57 | Q44: =N44-O44-P44 -> 9395.07 | R44: =[1]июнь24!AC96 -> 81.068824 | S44: =D44/H44*I44-K44-2077.24 -> 12529.36 | T44: =F44/H44*I44 -> 10000 | U44: =T44+S44 -> 22529.36 | Y44: =N44+U44+V44+W44 -> 50000 | Z44: =Y44-O44-P44-Q44-X44 -> 22529.36 | AA44: 12600 | AC44: =R44+Z44-AA44-AB44 -> 10010.429
A45: Оператор по качеству | B45: Мазмаева Елена Николаевна | C45: 21890 | D45: =E45-C45 -> 18110 | E45: 40000 | F45: 15000 | G45: =E45+F45 -> 55000 | H45: 23 | I45: 23 | J45: 21890 | K45: 4378 | N45: =J45+K45+L45+M45 -> 26268 | O45: 3415 | P45: 9108.13 | Q45: =N45-O45-P45 -> 13744.87 | R45: =[1]июнь24!AC97 -> 2.56 | S45: =D45/H45*I45-K45 -> 13732 | T45: =F45/H45*I45 -> 15000 | U45: =T45+S45 -> 28732 | Y45: =N45+U45+V45+W45 -> 55000 | Z45: =Y45-O45-P45-Q45-X45 -> 28732 | AA45: 13700 | AC45: =R45+Z45-AA45-AB45 -> 15034.56
A46: Оператор | B46: Митченко Галина Николаевна | C46: 21891 | D46: =E46-C46 -> 18109 | E46: 40000 | F46: 10000 | G46: =E46+F46 -> 50000 | H46: 23 | I46: 23 | J46: 17785.63 | K46: 3557.13 | L46: 6442.8 | N46: =J46+K46+L46+M46 -> 27785.56 | O46: 3612 | P46: =8331.88+5604.8 -> 13936.68 | Q46: =N46-O46-P46 -> 10236.88 | R46: =[1]июнь24!AC98 -> 92.862941 | S46: =D46/H46*I46-K46-2337.43 -> 12214.44 | T46: =F46/H46*I46 -> 10000 | U46: =T46+S46 -> 22214.44 | Y46: =N46+U46+V46+W46 -> 50000 | Z46: =Y46-O46-P46-Q46-X46 -> 22214.44 | AA46: 12300 | AC46: =R46+Z46-AA46-AB46 -> 10007.303
B47: Отдел обучения водителей | C47: =C48 -> 26250 | D47: =D48 -> 123750 | E47: =E48 -> 150000 | F47: =F48 -> 0 | G47: =G48 -> 150000 | H47: =H48 -> 23 | I47: =I48 -> 23 | J47: =J48 -> 26250 | ... AC47: =AC48 -> 80.6
A48: специалист по развитию и обучению персонала | B48: Рожин Дмитрий Валерьевич | C48: 26250 | D48: 123750 | E48: =C48+D48 -> 150000 | F48: 0 | G48: =E48+F48 -> 150000 | H48: 23 | I48: 23 | J48: 26250 | K48: 5250 | N48: =J48+K48+L48+M48 -> 31500 | O48: 4095 | P48: 10922.35 | Q48: =N48-O48-P48 -> 16482.65 | R48: =[1]июнь24!AC100 -> 80.6 | S48: =D48/H48*I48-K48 -> 118500 | T48: =F48/H48*I48 -> 0 | U48: =T48+S48 -> 118500 | Y48: =N48+U48+V48+W48 -> 150000 | Z48: =Y48-O48-P48-Q48-X48 -> 118500 | AA48: 118500 | AB48: 0 | AC48: =R48+Z48-AA48-AB48 -> 80.6

Sheet РД4, ГМ
A3: № п/п | B3: Должность | C3: ФИО | E3: Премия | Q3: ИТОГО зарплата | R3: Удержяния | S3: Премия к выплате
E4: Уровни выполнени КПЭ и ставка вознаграждения
E5: ВАЛОВАЯ ПРИБЫЛЬ | H5: ПЕРЕМЕННЫЕ РАСХОДЫ, Д-4 | K5: Выполнение плана по Марже | O5: Итоговая ставка вознаграждения | P5: ИТОГО ПРЕМИЯ
D6: ОКЛАД | E6: План | F6: Факт | G6: Перевыполнение плана по ВП | H6: План (Фонд по фактическому пробегу, руб) | I6: Факт | J6: Перевыполнение плана | K6: План по маржинальной прибыли (ТБУ) | L6: Факт по маржинальной прибыли | M6: Сумма перевыполнения | N6: % премии
A7: 1 | B7: РД4 | C7: ='Д4-ФОТ '!B6 -> Сайфетдинов Эдуард Кияметдинович | D7: ='Д4-ФОТ '!Y6 -> 222222.23 | E7: 192188490 | F7: ='НК, РГ'!H59 -> 1.5916632e+08 | G7: =F7-E7 -> -33022170 | H7: ='НК, РГ'!J59 -> 59997543 | I7: ='НК, РГ'!K59 -> 55504416 | J7: =H7-I7 -> 4493126.9 | K7: =E7-H7 -> 1.3219095e+08 | L7: =F7-I7 -> 1.036619e+08 | M7: =L7-K7 -> -28529043 | N7: 0 | O7: =M7*N7 -> 0 | P7: =O7 -> 0 | Q7: =D7+P7 -> 222222.23 | R7: 0 | S7: =P7-R7 -> 0

Sheet Д4-ФОТ 
A1: ТРАНСПОРТНАЯ КОМПАНИЯ
A2: Подразделение | C2: Оклад | F2: Премия (переменная часть) | G2: ИТОГО ФОТ | H2: Отраб.время | J2: Оф.з/п | O2: НДФЛ на оф. | P2: Аванс на карту | Q2: З/п на карту | R2: Остаток на начало расчетного периода | S2: Начислено по положению | V2: Отпускные | W2: Прочие доплаты | X2: Удержания | Y2: Итого начислено | Z2: К выплате через кассу | AA2: Выплачено через кассу | AC2: Остаток на конец расчетного периода | AD2: примечание
A3: Должность | B3: Сотрудник | C3: Офиц | D3: Неофиц | E3: ОКЛАД Всего | H3: План | I3: Факт | J3: Оклад | K3: Премия | L3: Отпускные | M3: Комп. при увольнении по соглашению сторон | N3: Итого | S3: Оклад | T3: Премия | U3: Итого
A4: Д4-Производственный департамент | C4: =C5+C7+C17+C33 -> 851975 | D4: =D5+D7+D17+D33 -> 2012150 | E4: =E5+E7+E17+E33 -> 2864125 | F4: =F5+F7+F17+F33 -> 450000.02 | G4: =G5+G7+G17+G33 -> 3314125 | H4: =H5+H7+H17+H33 -> 648 | I4: =I5+I7+I17+I33 -> 538 | J4: =J5+J7+J17+J33 -> 668409.51 | ... AC4: =AC5+AC7+AC17+AC33 -> 2089006.1
B5: РД4 | C5: =SUM(C6:C6) -> 47250 | D5: =SUM(D6:D6) -> 202750 | E5: =SUM(E6:E6) -> 250000 | F5: =SUM(F6:F6) -> 0.02 | G5: =SUM(G6:G6) -> 250000.02 | H5: =SUM(H6:H6) -> 18 | I5: =SUM(I6:I6) -> 18 | J5: =SUM(J6:J6) -> 34125 | ... AC5: =SUM(AC6:AC6) -> 180737
A6: РД4 | B6: Сайфетдинов Эдуард Кияметдинович | C6: 47250 | D6: 202750 | E6: 250000 | F6: 0.02 | G6: 250000.02 | H6: 18 | I6: 18 | J6: 34125 | K6: 6825 | L6: 0 | N6: 40950 | O6: 5324 | P6: 4567 | Q6: 31059 | R6: 27.271818 | S6: 181272.23 | U6: 181272.23 | X6: 562.5 | Y6: 222222.23 | Z6: 180709.73 | AC6: 180737
B7: Производственный отдел | C7: =SUM(C8:C16) -> 216300 | D7: =SUM(D8:D16) -> 833700 | E7: =SUM(E8:E16) -> 1050000 | F7: =SUM(F8:F16) -> 0 | G7: =SUM(G8:G16) -> 1050000 | H7: =SUM(H8:H16) -> 162 | I7: =SUM(I8:I16) -> 144 | J7: =SUM(J8:J16) -> 176925 | ... AC7: =SUM(AC8:AC16) -> 739458.94
A8: НК | B8: Базыгутдинов Дамир Асафутинович | C8: 26250 | D8: 73750 | E8: 100000 | G8: 100000 | H8: 18 | I8: 18 | J8: 13125 | K8: 2625 | L8: 0 | N8: =J8+K8+L8+M8 -> 15750 | O8: 1800 | P8: 0 | Q8: =N8-O8-P8 -> 13950 | R8: 77.871176 | S8: =65*2000-J8-K8-14889.7 -> 99360.3 | T8: ='НК, РГ'!AB54 -> 65000 | U8: =T8+S8 -> 164360.3 | Y8: =N8+U8+V8+W8 -> 180110.3 | Z8: 97360.3 | AC8: 97438.171
A9: РГ Д4 | B9: Бикмуллин Айрат Равилевич | C9: 29400 | D9: 120600 | E9: 150000 | G9: 150000 | H9: 18 | I9: 18 | J9: 29400 | K9: 5880 | L9: 0 | N9: =J9+K9+L9+M9 -> 35280 | O9: 4587 | P9: 9946.33 | Q9: =N9-O9-P9 -> 20746.67 | R9: 42.175378 | S9: =D9/H9*I9-K9 -> 114720 | U9: =T9+S9 -> 114720 | Y9: =N9+U9+V9+W9 -> 150000 | Z9: 114720 | AC9: 114762.18
A10: НК | B10: Веденяпин Сергей Юрьевич | C10: 26250 | D10: 73750 | E10: 100000 | F10: 0 | G10: 100000 | H10: 18 | I10: 18 | J10: 26250 | K10: 5250 | L10: 0 | N10: =J10+K10+L10+M10 -> 31500 | O10: 4095 | P10: 4440.66 | Q10: =N10-O10-P10 -> 22964.34 | R10: 99.36 | S10: =65*2000-J10-K10 -> 98500 | T10: ='НК, РГ'!AB56 -> 65000 | U10: =T10+S10 -> 163500 | Y10: =N10+U10+V10+W10 -> 195000 | Z10: 98500 | AC10: 98599.36
A11: НК | B11: Козин Александр Павлович | C11: 26250 | D11: 73750 | E11: 100000 | G11: 100000 | H11: 18 | I11: 0 | J11: 0 | K11: 0 | L11: 10064.83 | N11: =J11+K11+L11+M11 -> 10064.83 | O11: 4110.86 | P11: 5953.97 | Q11: =N11-O11-P11 -> 0 | R11: 76.190476 | U11: =T11+S11 -> 0 | Y11: =N11+U11+V11+W11 -> 10064.83 | Z11: -9.094947e-13 | AC11: 76.190476
A12: НК | B12: Николаев Игорь Евгеньевич | C12: 26250 | D12: 73750 | E12: 100000 | F12: 0 | G12: 100000 | H12: 18 | I12: 18 | J12: 26250 | K12: 5250 | L12: 0 | N12: =J12+K12+L12+M12 -> 31500 | O12: 4095 | P12: 8881.33 | Q12: =N12-O12-P12 -> 18523.67 | R12: 95.856957 | S12: =65*2000-J12-K12 -> 98500 | T12: ='НК, РГ'!AB52 -> 65000 | U12: =T12+S12 -> 163500 | Y12: =N12+U12+V12+W12 -> 195000 | Z12: 98500 | AC12: 98595.857
A13: НК | B13: Кочетов Александр Валерьевич | C13: 26250 | D13: 73750 | E13: 100000 | G13: 100000 | H13: 18 | I13: 18 | J13: 26250 | K13: 5250 | L13: 0 | N13: =J13+K13+L13+M13 -> 31500 | O13: 3913 | P13: 8881.33 | Q13: =N13-O13-P13 -> 18705.67 | R13: 35.98 | S13: =70*2000-J13-K13 -> 108500 | T13: ='НК, РГ'!AB55 -> 77000 | U13: =T13+S13 -> 185500 | Y13: =N13+U13+V13+W13 -> 217000 | Z13: 110500 | AC13: 110535.98
A14: РГ Д4 | B14: Мулындин Денис Михайлович | D14: 150000 | E14: 150000 | G14: 150000 | H14: 18 | I14: 18 | N14: =J14+K14+L14+M14 -> 0 | Q14: =N14-O14-P14 -> 0 | R14: 44.799267 | S14: =D14/H14*I14-K14 -> 150000 | U14: =T14+S14 -> 150000 | Y14: =N14+U14+V14+W14 -> 150000 | Z14: 150000 | AA14: 150000 | AC14: 44.799267
A15: НК | B15: Попов Андрей Викторович | C15: 26250 | D15: 73750 | E15: 100000 | G15: 100000 | H15: 18 | I15: 18 | J15: 26250 | K15: 5250 | L15: 0 | N15: =J15+K15+L15+M15 -> 31500 | O15: 4095 | P15: 8881.33 | Q15: =N15-O15-P15 -> 18523.67 | R15: 87.247059 | S15: =67*2000-J15-K15 -> 102500 | T15: ='НК, РГ'!AB53 -> 60300 | U15: =T15+S15 -> 162800 | Y15: =N15+U15+V15+W15 -> 194300 | Z15: 104500 | AC15: 104587.25
A16: РГ Д4 | B16: Рашитов Рамиль Камилович | C16: 29400 | D16: 120600 | E16: 150000 | G16: 150000 | H16: 18 | I16: 18 | J16: 29400 | K16: 5880 | L16: 0 | N16: =J16+K16+L16+M16 -> 35280 | O16: 4405 | P16: 9946.33 | Q16: =N16-O16-P16 -> 20928.67 | R16: 99.161219 | S16: =D16/H16*I16-K16 -> 114720 | U16: =T16+S16 -> 114720 | Y16: =N16+U16+V16+W16 -> 150000 | Z16: 114720 | AC16: 114819.16
B17: Технический отдел | C17: =SUM(C18:C32) -> 380050 | D17: =SUM(D18:D32) -> 744950 | E17: =SUM(E18:E32) -> 1125000 | F17: =SUM(F18:F32) -> 285000 | G17: =SUM(G18:G32) -> 1410000 | H17: =SUM(H18:H32) -> 270 | I17: =SUM(I18:I32) -> 254 | J17: =SUM(J18:J32) -> 319760.79 | ... AC17: =SUM(AC18:AC32) -> 907341.19
A18: Механик - контролер | B18: Асулханов Айрат Анварович | C18: 23630 | D18: 21370 | E18: 45000 | F18: 35000 | G18: 80000 | H18: 18 | I18: 18 | J18: 16910.72 | K18: 3150.67 | L18: 6869.17 | N18: 26930.56 | O18: 3501 | P18: 10600.72 | Q18: 12828.84 | R18: 11.570435 | S18: 18219.33 | T18: 35000 | U18: =S18+T18 -> 53219.33 | Y18: =N18+U18 -> 80149.89 | Z18: 53219.33 | AC18: 53230.9
A19: Инженер-механик | B19: Габитов Фаниль Фаргатович | C19: 26250 | D19: 53750 | E19: 80000 | F19: 0 | G19: 80000 | H19: 18 | I19: 18 | J19: 11666.67 | K19: 2333.33 | L19: 14954.38 | N19: 28954.38 | O19: 3764 | P19: 8880.33 | Q19: 16310.05 | R19: 53.944211 | S19: 51045.62 | T19: =мех!R24 -> 83700 | U19: =S19+T19 -> 134745.62 | X19: =мех!T24 -> 3000 | Y19: =N19+U19 -> 163700 | Z19: 51045.62 | AC19: 51099.564
A20: Механик - контролер | B20: Галимов Ильнур Ирикович | C20: 23630 | D20: 21370 | E20: 45000 | F20: 35000 | G20: 80000 | H20: 18 | I20: 8 | J20: 13760.06 | K20: 2520.53 | L20: 16205.08 | N20: 32485.67 | O20: 11111.8 | P20: 21373.87 | Q20: 0 | R20: 63.656106 | S20: 6977.2478 | T20: 15555.556 | U20: =S20+T20 -> 22532.803 | Y20: =N20+U20 -> 55018.473 | Z20: 22532.803 | AC20: 22596.459
A21: Механик - контролер | B21: Ганеев Ильнур Асгатевич | C21: 23630 | D21: 21370 | E21: 45000 | F21: 35000 | G21: 80000 | H21: 18 | I21: 17 | J21: 23212.06 | K21: 4410.93 | L21: 23567.03 | N21: 51190.02 | O21: 6654 | P21: 44536.02 | Q21: 0 | R21: 93.855439 | S21: 15771.848 | T21: 33055.556 | U21: =S21+T21 -> 48827.403 | Y21: =N21+U21 -> 100017.42 | Z21: 48827.403 | AC21: 48921.259
A22: Механик - контролер | B22: Закиев Ренат Марселевич | C22: 23630 | D22: 21370 | E22: 45000 | F22: 35000 | G22: 80000 | H22: 18 | I22: 18 | J22: 26625.28 | K22: 5093.58 | L22: 0 | N22: 31718.86 | O22: 4123 | P22: 10600.72 | Q22: 16995.14 | R22: 68.779524 | S22: 14438.53 | T22: 35000 | U22: =S22+T22 -> 49438.53 | Y22: =N22+U22 -> 81157.39 | Z22: 49438.53 | AC22: 49507.31
A23: Инженер-механик | B23: Кияметдинов Фарит Рустамович | C23: 26250 | D23: 53750 | E23: 80000 | F23: 0 | G23: 80000 | H23: 18 | I23: 18 | J23: 26250 | K23: 5250 | L23: 0 | N23: 31500 | O23: 4095 | P23: 8881.33 | Q23: 18523.67 | R23: 14.39 | S23: 48500 | T23: =мех!R25 -> 92460 | U23: =S23+T23 -> 140960 | X23: =мех!T25 -> 5000 | Y23: =N23+U23 -> 172460 | Z23: 48500 | AC23: 48514.39
A24: Начальник технического отдела | B24: Мавлиев Марат Ильшатович | C24: 30000 | D24: 120000 | E24: 150000 | F24: 0 | G24: 150000 | H24: 18 | I24: 18 | J24: 30000 | K24: 6000 | L24: 0 | N24: 36000 | O24: 4680 | P24: 10149.67 | Q24: 21170.33 | R24: 9.3085714 | S24: 114000 | T24: 0 | U24: =S24+T24 -> 114000 | Y24: =N24+U24 -> 150000 | Z24: 114000 | AC24: 114009.31
A25: ведущий механик | B25: Набиев Рустам Нариманович | C25: 26250 | D25: 123750 | E25: 150000 | G25: 150000 | H25: 18 | I25: 18 | J25: 26250 | K25: 5250 | L25: 15095.64 | N25: 46595.64 | O25: 5875 | P25: 6661 | Q25: 34059.64 | R25: 85.714286 | S25: 118500 | T25: 0 | U25: =S25+T25 -> 118500 | Y25: =N25+U25 -> 165095.64 | Z25: 118500 | AC25: 118585.71
A26: Инженер-механик | B26: Нурмухаметов Айрат Ринатович | C26: 26250 | D26: 53750 | E26: 80000 | F26: 0 | G26: 80000 | H26: 18 | I26: 18 | J26: 26250 | K26: 5250 | L26: 0 | N26: 31500 | O26: 3549 | P26: 4440.66 | Q26: 23510.34 | R26: 28.571429 | S26: 48500 | T26: =мех!R26 -> 97500 | U26: =S26+T26 -> 146000 | Y26: =N26+U26 -> 177500 | Z26: 48500 | AC26: 48528.571
A27: Старший механик - контролер | B27: Сафуанов Амир Мансурович | C27: 26250 | D27: 53750 | E27: 80000 | F27: 40000 | G27: 120000 | H27: 18 | I27: 18 | J27: 26250 | K27: 5250 | L27: 0 | N27: 31500 | O27: 4095 | P27: 8881.33 | Q27: 18523.67 | R27: 0.79 | S27: 48500 | T27: 40000 | U27: =S27+T27 -> 88500 | Y27: =N27+U27 -> 120000 | Z27: 88500 | AC27: 88500.79
A28: Инженер-механик | B28: Свистунов Дмитрий Петрович | C28: 26250 | D28: 53750 | E28: 80000 | F28: 0 | G28: 80000 | H28: 18 | I28: 18 | J28: 26250 | K28: 5250 | L28: 0 | N28: 31500 | O28: 3549 | P28: 5921.18 | Q28: 22029.82 | R28: 84.447619 | S28: 48500 | T28: =мех!R27 -> 172620 | U28: =S28+T28 -> 221120 | X28: =мех!T27 -> 4000 | Y28: =N28+U28 -> 252620 | Z28: 48500 | AC28: 48584.448
A29: Механик - контролер | B29: Спиридонов Алик Альбертович | C29: 23630 | D29: 21370 | E29: 45000 | F29: 35000 | G29: 80000 | H29: 18 | I29: 18 | J29: 12602.67 | K29: 2520.53 | L29: 0 | N29: 15123.2 | O29: 0 | P29: 0 | Q29: 15123.2 | R29: 69.700439 | S29: 17600.25 | T29: 35000 | U29: =S29+T29 -> 52600.25 | Y29: =N29+U29 -> 67723.45 | Z29: 52600.25 | AC29: 52669.95
A30: Главный механик | B30: Тятюшкин Иван Иванович | C30: 29400 | D30: 80600 | E30: 110000 | F30: 0 | G30: 110000 | H30: 18 | I30: 13 | J30: 21233.33 | K30: 4246.67 | L30: 0 | N30: 25480 | O30: 3312 | P30: 2841.67 | Q30: 19326.33 | R30: 0 | S30: 53964.441 | T30: 0 | U30: =S30+T30 -> 53964.441 | Y30: =N30+U30 -> 79444.441 | Z30: 53964.441 | AC30: 53964.441
A31: специалист по технической документации | B31: Фалахова Алсу Халиловна | C31: 22500 | D31: 22500 | E31: 45000 | F31: 35000 | G31: 80000 | H31: 18 | I31: 18 | J31: 22500 | K31: 4500 | L31: 0 | N31: 27000 | O31: 3328 | P31: 7612 | Q31: 16060 | R31: 54.72532 | S31: 18000 | T31: 35000 | U31: =S31+T31 -> 53000 | Y31: =N31+U31 -> 80000 | Z31: 53000 | AC31: 53054.725
A32: специалист по технической документации | B32: Хайруллина Екатерина Сергеевна | C32: 22500 | D32: 22500 | E32: 45000 | F32: 35000 | G32: 80000 | H32: 18 | I32: 18 | J32: 10000 | K32: 2000 | L32: 12428.36 | N32: 24428.36 | O32: 2629 | P32: 7612 | Q32: 14187.36 | R32: 1.7203313 | S32: 20571.64 | T32: 35000 | U32: =S32+T32 -> 55571.64 | Y32: =N32+U32 -> 80000 | Z32: 55571.64 | AC32: 55573.36
B33: Отдел сопровождения водителей | C33: =SUM(C34:C44) -> 208375 | D33: =SUM(D34:D44) -> 230750 | E33: =SUM(E34:E44) -> 439125 | F33: =SUM(F34:F44) -> 165000 | G33: =SUM(G34:G44) -> 604125 | H33: =SUM(H34:H44) -> 198 | I33: =SUM(I34:I44) -> 122 | J33: =SUM(J34:J44) -> 137598.72 | ... AC33: =SUM(AC34:AC44) -> 261468.98
B34: Борейко Оксана Ивановна | H34: 18 | I34: 0 | J34: 0 | K34: 0 | L34: 0 | N34: 0 | O34: 0 | P34: 0 | Q34: 0 | R34: 13.47 | S34: 0 | U34: 0 | Y34: 0 | Z34: 0 | AC34: 13.47
A35: Оператор | B35: Гильфанова Светлана Сергеевна | C35: 22500 | D35: 27500 | E35: 50000 | F35: 15000 | G35: 65000 | H35: 18 | I35: 18 | J35: 23602.04 | K35: 4500 | L35: 0 | N35: 28102.04 | O35: 3653 | P35: 10747.04 | Q35: 13702 | R35: 21.16 | S35: 23000 | T35: 15000 | U35: 38000 | Y35: 66102.04 | Z35: 38000 | AC35: 38021.16
B36: Ерошкина Виктория Константиновна | G36: 0 | H36: 18 | N36: 0 | Q36: 0 | R36: 46.753247 | S36: 0 | T36: 0 | U36: 0 | Y36: 0 | Z36: 0 | AC36: 46.753247
A37: Оператор | B37: Ковалева Юлия Сергеевна | C37: 22500 | D37: 31250 | E37: 53750 | F37: 10000 | G37: 63750 | H37: 18 | I37: 18 | J37: 13602.14 | K37: 2500 | L37: 12936.14 | N37: 29038.28 | O37: 3775 | P37: 9224.04 | Q37: 16039.24 | R37: 76.293529 | S37: 42480.527 | T37: 10000 | U37: 52480.527 | Y37: 81518.807 | Z37: 52480.527 | AC37: 52556.82
A38: Водитель-курьер | B38: Костин Сергей Васильевич | C38: 25875 | D38: 9500 | E38: 35375 | F38: 60000 | G38: 95375 | H38: 18 | I38: 18 | J38: 25875 | K38: 4500 | L38: 0 | N38: 30375 | O38: 3168 | P38: 8754.5 | Q38: 18452.5 | R38: 84.16 | S38: 5000 | T38: 60000 | U38: 65000 | Y38: 95375 | Z38: 65000 | AC38: 65084.16
A39: Оператор | B39: Костина Рузиля Равилевна | C39: 22500 | D39: 27500 | E39: 50000 | F39: 15000 | G39: 65000 | H39: 18 | I39: 18 | J39: 17245.89 | K39: 3000 | L39: 0 | N39: 20245.89 | O39: 2268 | P39: 8156 | Q39: 9821.89 | R39: 68.873636 | S39: 24500 | T39: 15000 | U39: 39500 | Y39: 59745.89 | Z39: 39500 | AC39: 39568.874
A40: Оператор | B40: Кузьмина Гузель Назиповна | C40: 22500 | D40: 27500 | E40: 50000 | F40: 15000 | G40: 65000 | H40: 18 | I40: 0 | J40: 2171.61 | K40: 0 | L40: 0 | N40: 2171.61 | O40: 282 | P40: 0 | Q40: 1889.61 | R40: 20.175966 | S40: 0 | T40: 0 | U40: 0 | Y40: 2171.61 | Z40: 0 | AC40: 20.175966
A41: Оператор | B41: Латышева Анна Ивановна | C41: 22500 | D41: 27500 | E41: 50000 | G41: 50000 | H41: 18 | I41: 4 | J41: 4500 | K41: 900 | N41: 5400 | O41: 702 | P41: 0 | Q41: 4698 | R41: 0 | S41: 5811.1111 | T41: 0 | U41: 5811.1111 | Y41: 11211.111 | Z41: 5811.1111 | AC41: 5811.1111
A42: Оператор по качеству | B42: Мазмаева Елена Николаевна | C42: 25000 | D42: 25000 | E42: 50000 | F42: 25000 | G42: 75000 | H42: 18 | I42: 18 | J42: 25000 | K42: 5000 | L42: 0 | N42: 30000 | O42: 3900 | P42: 8458.22 | Q42: 17641.78 | R42: 0.31 | S42: 20000 | T42: 25000 | U42: 45000 | Y42: 75000 | Z42: 45000 | AC42: 45000.31
A43: Оператор | B43: Митченко Галина Николаевна | C43: 22500 | D43: 27500 | E43: 50000 | F43: 15000 | G43: 65000 | H43: 18 | I43: 18 | J43: 12352.04 | K43: 2250 | L43: 13256.32 | N43: 27858.36 | O43: 3622 | P43: 5852.04 | Q43: 18384.32 | R43: 65.492941 | S43: 23243.68 | T43: 15000 | U43: 38243.68 | Y43: 66102.04 | Z43: 38243.68 | AA43: 23300 | AB43: 15000 | AC43: 9.1729412
A44: Оператор | B44: Шек Дарья Витальевна | C44: 22500 | D44: 27500 | E44: 50000 | F44: 10000 | G44: 60000 | H44: 18 | I44: 10 | J44: 13250 | K44: 0 | L44: 24523.58 | N44: 37773.58 | O44: 4911 | P44: 32862.58 | Q44: 0 | R44: 59.192251 | S44: 15277.778 | T44: 0 | U44: 15277.778 | Y44: 53051.358 | Z44: 15277.778 | AC44: 15336.97

Sheet Зарплата НК по месяцам
A2: Ф.И.О. | B2: Итого зарплата по месяцам
B3: январь,24 | C3: февраль,24 | D3: март,24 | E3: апрель,24 | F3: май,24 | G3: июнь,24 | H3: июнь,24
A4: Абрамчев Дмитрий Владимирович | B4: 99500 | C4: =VLOOKUP(A4,A25:B40,2) -> 100000 | D4: =B43 -> 60430.37 | E4: =B61 -> 0 | F4: 0 | G4: 0 | H4: 0
A5: Ардашов Дмитрий Сергеевич | B5: 96189 | C5: =VLOOKUP(A5,A26:B41,2) -> 100000 | D5: =B44 -> 106400 | E5: =B62 -> 95000 | F5: 100000 | G5: 27638.55
A6: Базыгутдинов Дамир Асафутинович | C6: =VLOOKUP(A6,A27:B43,2) -> 108600 | D6: =B45 -> 85000 | E6: =B63 -> 110000 | F6: 145600 | G6: 266400 | H6: ='НК, РГ'!#REF! -> #REF!
A7: Веденяпин Сергей Юрьевич | E7: =B64 -> 75000 | F7: 100000 | G7: 188000 | H7: ='НК, РГ'!#REF! -> #REF!
A8: Захаров Андрей Юрьевич | B8: 86849 | C8: =VLOOKUP(A8,A27:B43,2) -> 75000 | D8: =B46 -> 84524 | E8: =B65 -> 158600 | F8: 177000 | G8: 107500 | H8: ='НК, РГ'!#REF! -> #REF!
A9: Зыков Андрей Юрьевич | B9: 100000 | C9: =VLOOKUP(A9,A28:B44,2) -> 105000 | D9: =B47 -> 109400 | E9: =B66 -> 100000 | F9: 192200 | G9: 230600 | H9: ='НК, РГ'!#REF! -> #REF!
A10: Измайлов Владимир Владимирович | B10: 75000 | C10: =VLOOKUP(A10,A29:B45,2) -> 15097.77 | D10: =B48 -> 0 | E10: =B67 -> 0 | F10: 0 | G10: 0 | H10: 0
A11: Кабильков Евгений Михайлович | B11: 90403 | C11: =VLOOKUP(A11,A30:B46,2) -> 90300 | D11: =B49 -> 100000 | E11: =B68 -> 35117.59 | F11: 0 | G11: 0 | H11: 0
A12: Козлов Максим Юрьевич | E12: =B69 -> 30000 | F12: 100000 | G12: 100000 | H12: ='НК, РГ'!#REF! -> #REF!
A13: Кочетов Александр Валерьевич | B13: 179600 | C13: =VLOOKUP(A13,A31:B47,2) -> 244200 | D13: =B50 -> 238200 | E13: =B70 -> 340600 | F13: 269500 | G13: 328600 | H13: ='НК, РГ'!#REF! -> #REF!
A14: Минаков Ильхам Наилович | B14: 125000 | C14: =VLOOKUP(A14,A32:B48,2) -> 92972.82 | D14: =B51 -> 0 | E14: =B71 -> 0 | F14: 0 | G14: 0 | H14: 0
A15: Морозов Виктор Сергеевич | D15: =B52 -> 30000 | E15: =B72 -> 22063.89 | F15: 0 | G15: 0 | H15: 0
A16: Набиуллин Фидус Фанзильевич | B16: 100000 | C16: =B35 -> 97866 | D16: =B54 -> 100000 | E16: =B74 -> 120000 | F16: 100000 | G16: 235300 | H16: ='НК, РГ'!#REF! -> #REF!
A17: Пахулин Андрей Михайлович | B17: 112191 | C17: =B36 -> 87500 | D17: =B55 -> 98578 | E17: =B75 -> 90000 | F17: 100000 | G17: 154000 | H17: ='НК, РГ'!#REF! -> #REF!
A18: Попов Андрей Викторович | E18: =B76 -> 100000 | F18: 150000 | G18: 100000 | H18: ='НК, РГ'!#REF! -> #REF!
A19: Тищенко Юрий Николаевич | B19: 84160 | C19: =B38 -> 85000 | D19: =B57 -> 93662.16 | E19: =B78 -> 0 | F19: 0 | G19: 0 | H19: 0
A20: Токунов Михаил Сергеевич | B20: 85000 | C20: =B39 -> 90000 | D20: =B58 -> 50000 | E20: =B79 -> 48791.4 | F20: 0 | G20: 0 | H20: 0
A21: Федоров Евгений Александрович | F21: 70000 | G21: 146000 | H21: ='НК, РГ'!#REF! -> #REF!
A22: Хузин Айнур Наилович | B22: 99738 | C22: =B40 -> 100000 | D22: =B59 -> 110000 | E22: =B80 -> 110000 | F22: 21592.48 | G22: 0 | H22: 0
B23: =SUM(B4:B22) -> 1333630 | C23: =SUM(C4:C22) -> 1391536.6 | D23: =SUM(D4:D22) -> 1266194.5 | E23: =SUM(E4:E22) -> 1435172.9 | F23: =SUM(F4:F22) -> 1525892.5 | G23: =SUM(G4:G22) -> 1884038.6 | H23: =SUM(H4:H22) -> #REF!
A25: Абрамчев Дмитрий Владимирович | B25: 100000
A26: Ардашов Дмитрий Сергеевич | B26: 100000
A27: Базыгутдинов Дамир Асафутинович | B27: 108600
A28: Захаров Андрей Юрьевич | B28: 75000
A29: Зыков Андрей Юрьевич | B29: 105000
A30: Измайлов Владимир Владимирович | B30: 15097.77
A31: Кабильков Евгений Михайлович | B31: 90300
A32: Кочетов Александр Валерьевич | B32: 244200
A33: Минаков Ильхам Наилович | B33: 92972.82
A34: Мулындин Денис Михайлович | B34: 178000
A35: Набиуллин Фидус Фанзильевич | B35: 97866
A36: Пахулин Андрей Михайлович | B36: 87500
... A40: Хузин Айнур Наилович | B40: 100000
B41: =SUM(B25:B40) -> 1768036.6
A43: Абрамчев Дмитрий Владимирович | B43: 60430.37
A44: Ардашов Дмитрий Сергеевич | B44: 106400
A45: Базыгутдинов Дамир Асафутинович | B45: 85000
A46: Захаров Андрей Юрьевич | B46: 84524
A47: Зыков Андрей Юрьевич | B47: 109400
A48: Измайлов Владимир Владимирович | B48: 0
A49: Кабильков Евгений Михайлович | B49: 100000
A50: Кочетов Александр Валерьевич | B50: 238200
A51: Минаков Ильхам Наилович | B51: 0
A52: Морозов Виктор Сергеевич | B52: 30000
A53: Мулындин Денис Михайлович | B53: 177000
A54: Набиуллин Фидус Фанзильевич | B54: 100000
... A59: Хузин Айнур Наилович | B59: 110000
B60: =SUM(B43:B59) -> 1655194.5
A61: Абрамчев Дмитрий Владимирович | B61: 0
A62: Ардашов Дмитрий Сергеевич | B62: 95000
A63: Базыгутдинов Дамир Асафутинович | B63: 110000
A64: Веденяпин Сергей Юрьевич | B64: 75000
A65: Захаров Андрей Юрьевич | B65: 158600
A66: Зыков Андрей Юрьевич | B66: 100000
A67: Измайлов Владимир Владимирович | B67: 0
A68: Кабильков Евгений Михайлович | B68: 35117.59
A69: Козлов Максим Юрьевич | B69: 30000
A70: Кочетов Александр Валерьевич | B70: 340600
A71: Минаков Ильхам Наилович | B71: 0
A72: Морозов Виктор Сергеевич | B72: 22063.89
... A80: Хузин Айнур Наилович | B80: 110000
B81: =SUM(B61:B80) -> 1811672.9

Sheet механики
A1: Калькулятор расчета зарплаты механикам
W2: =#REF!/#REF! -> #REF!
A3: Справочные коэффициенты для механиков
B5: тарифная ставка | C5: р/тс | F5: Пробег | G5: Затраты на ТОиР | I5: Соблюдение графика ТО и регламентного ремонта. | M5: Процент выполнения плана и коэффициент: | O5: менее 50% | P5: 50-89,99% | Q5: 90-94,99% | R5: 95-99,99% | S5: 100% и более | Y5: KPI, % влияния | Z5: 1. Соблюдение плановых интервалов замен шин, расходников и агрегатов (допускается доля внеплановых замен не более 5%). Отклонение от нормы ходимости +- 5%. | AA5: 0.5 | AB5: 45000
B6: главный механик | C6: 450 | E6: План | F6: 18000 | G6: 5.8 | I6: Кол-во ТС с вовремя проведенным обслуживанием/общее кол-во ТС утвержденное в плане ТО | M6: Показатель | N6: Вес | Z6: 2. Затраты на ТО и Р | AA6: 0.3 | AB6: 27000
B7: механик по ремонту | C7: 350 | M7: План Пробега | N7: 520 | O7: 0 | P7: 0.5 | Q7: 0.8 | R7: 0.9 | S7: 1 | Z7: 3. Смарт задачи | AA7: 0.2 | AB7: 18000
M8: Затраты на ТОиР | N8: 390 | O8: 0 | P8: 0.5 | Q8: 0.8 | R8: 0.9 | S8: 1 | AB8: =SUM(AB5:AB7) -> 90000
M9: Соблюдение графика ТО | N9: 390 | O9: 0 | P9: 0.5 | Q9: 0.8 | R9: 0.9 | S9: 1
A14: № п/п | B14: Должность | C14: ФИО | D14: Оклад | G14: Премия | T14: ИТОГО НАЧИСЛЕНО | U14: Удежания | V14: ИТОГО К ВЫПЛАТЕ
G15: Уровни выполнени КПЭ и ставка вознаграждения
G16: =Z5 -> 1. Соблюдение плановых интервалов замен шин, расходников и агрегатов (допускается доля внеплановых замен не более 5%). Отклонение от нормы ходимости +- 5%. | J16: =Z6 -> 2. Затраты на ТО и Р | M16: =Z7 -> 3. Смарт задачи | Q16: Итоговая ставка вознаграждения | R16: Перерасчет за прошлый месяц | S16: ИТОГО ПРЕМИЯ
D17: кол-во ТС | E17: ставка р/тс | F17: начислен оклад | H17: Уровень выполнения КПЭ | I17: ставка вознаграждения | J17: Факт р/км | K17: Уровень выполнения КПЭ | L17: ставка вознаграждения | M17: План | N17: Факт | O17: Уровень выполнения КПЭ | P17: ставка вознаграждения
A18: 4 | B18: главный механик | C18: Кузьмин А.В. | F18: 60000 | H18: 1 | I18: =AB5*H18 -> 45000 | J18: 12.3 | K18: =G$6/J18 -> 0.47154472 | L18: =AB6*K18 -> 12731.707 | O18: 1 | P18: =AB7*O18 -> 18000 | Q18: 90000 | S18: =Q18 -> 90000 | T18: =F18+S18 -> 150000 | V18: =T18-U18 -> 150000
A19: 4 | B19: ведущий механик по ремонту | C19: Аматыч Роберт Альбертович | F19: 60000 | Q19: 90000 | S19: =Q19 -> 90000 | T19: =F19+S19 -> 150000 | V19: =T19-U19 -> 150000
A21: № п/п | B21: Должность | C21: ФИО | D21: Оклад | G21: Премия | T21: ИТОГО НАЧИСЛЕНО | U21: Удежания | V21: ИТОГО К ВЫПЛАТЕ
G22: Уровни выполнени КПЭ и ставка вознаграждения
Q23: Итоговая ставка вознаграждения | R23: Перерасчет за прошлый месяц | S23: ИТОГО ПРЕМИЯ
D24: кол-во ТС | E24: ставка р/тс | F24: начислен оклад
A26: 6 | B26: механик по ремонту | C26: Набиев Рустам Нариманович | F26: 70000 | Q26: =I26+L26+P26 -> 0 | S26: 0 | T26: =F26+S26 -> 70000 | V26: =T26-U26 -> 70000
A27: 7 | Q27: =I27+L27+P27 -> 0 | S27: =D27*Q27 -> 0 | T27: =F27+S27 -> 0 | V27: =T27-U27 -> 0
A28: 8 | B28: механик по ремонту | Q28: =I28+L28+P28 -> 0 | S28: =D28*Q28 -> 0 | T28: =F28+S28 -> 0 | V28: =T28-U28 -> 0
F29: =SUM(F26:F28) -> 70000 | Q29: x | S29: =SUM(S26:S26) -> 0 | T29: =SUM(T26:T26) -> 70000 | V29: =SUM(V26:V26) -> 70000
F31: =F18+F19+F29 -> 190000 | S31: =S18+S19+S29 -> 180000 | T31: =T18+T19+T29 -> 370000

Sheet контролеры
A1: Калькулятор расчета зарплаты контролерам
A4: Справочные коэффициенты для контролеров
B6: Процент выполнения плана и коэффициент: | D6: менее 50% | E6: 50-89,99% | F6: 90-94,99% | G6: 95-99,99% | H6: 100% и более
B7: Показатель | C7: Вес
B8: Проведение ежегодного тех. осмтора ТС | C8: 1 | D8: 0 | E8: 0.5 | F8: 0.8 | G8: 0.9 | H8: 1
A14: № п/п | B14: Должность | C14: ФИО | D14: Оклад | E14: Премия | M14: ИТОГО ЗАРПЛАТА
E15: Уровни выполнени КПЭ и ставка вознаграждения
E16: Базовая премия (часть оклада, которая до этого была) | F16: Проведение ежегодного тех. осмтора ТС | L16: ИТОГО ПРЕМИЯ
F17: План | G17: факт | H17: Процент выполнения КПЭ | I17: коэффициент вознаграждения
A18: 7 | B18: старший контролер | C18: Сафуанов А. | D18: 54761.9 | E18: 40000 | F18: 35 | G18: 35 | H18: =G18/F18 -> 1 | I18: =IF(H18<50%,$D$8,IF(H18<90%,$E$8,IF(H18<95%,$F$8,IF(H18<100%,$G$8,IF(H18>=100%,$H$8))))) -> 1 | L18: =E18*I18 -> 40000 | M18: =D18+L18 -> 94761.9
F19: 1. Качество проведения осмотров ТС (Бонус от выставленных штрафов за выявленные нарушения. Сделка) | I19: 2. Качество выполнения складских операций (ежемесячная инвентаризация)
F20: уд. Вес | G20: % выполнения | H20: Сумма | I20: уд. Вес | J20: % выполнения | K20: Сумма
B21: контролер | C21: Базыгутдинов Дамир Асафутдинович | D21: 45000 | E21: 30000 | F21: 0.7 | G21: 1 | H21: =E21*F21*G21 -> 21000 | I21: 0.3 | J21: 1 | K21: =E21*I21*J21 -> 9000 | L21: =H21+K21 -> 30000 | M21: =D21+L21 -> 75000
B22: контролер | C22: Галимов Ильнур Ирикович | D22: 50000 | L22: =H22+K22 -> 0 | M22: =D22+L22 -> 50000 | N22: исп срок
B23: контролер | C23: Мирсанов Юрий Анатольевич | D23: 45000 | E23: 20000 | F23: 0.7 | G23: 1 | H23: =E23*F23*G23 -> 14000 | I23: 0.3 | J23: 1 | K23: =E23*I23*J23 -> 6000 | L23: =H23+K23 -> 20000 | M23: =D23+L23 -> 65000
B24: контролер | C24: Попов Юрий Андреевич | D24: 50000 | E24: 20000 | F24: 0.7 | G24: 1 | H24: =E24*F24*G24 -> 14000 | I24: 0.3 | J24: 1 | K24: =E24*I24*J24 -> 6000 | L24: =H24+K24 -> 20000 | M24: =D24+L24 -> 70000
D25: =SUM(D18:D24) -> 244761.9 | I25: x | L25: =SUM(L18:L24) -> 110000 | M25: =SUM(M18:M24) -> 354761.9
B26: контролер

Sheet СПТД, курьер
A1: Калькулятор расчета зарплаты СПТД и водителю-курьеру
A3: № п/п | B3: Должность | C3: ФИО | D3: Оклад | E3: Премия | P3: ИТОГО ЗАРПЛАТА
E5: Переменная часть | F5: 1. Отсутствие просроченной технической документации | I5: 2. Экономия бюджета на обеспечение технической документации и страхование | L5: 3. Отсутвие просроченных полисов ОСАГО, КАСКО, ответственность перевозчика | O5: ИТОГО ПРЕМИЯ
F6: уд. Вес | G6: % выполнения | H6: Сумма | I6: уд. Вес | J6: % выполнения | K6: Сумма | L6: уд. Вес | M6: % выполнения | N6: Сумма
C7: Тагиров Искандер Маратович | D7: 47400 | E7: 40000 | F7: 0.4 | G7: 1 | H7: =E7*F7*G7 -> 16000 | I7: 0.2 | J7: 1 | K7: =E7*I7*J7 -> 8000 | L7: 0.4 | M7: 1 | N7: =E7*L7*M7 -> 16000 | O7: =H7+K7+N7 -> 40000 | P7: =D7+O7 -> 87400
B8: СПТД | C8: Фалахова Алсу Халиловна | D8: 30000 | E8: 40000 | F8: 0.4 | G8: 1 | H8: =E8*F8*G8 -> 16000 | I8: 0.2 | J8: 1 | K8: =E8*I8*J8 -> 8000 | L8: 0.4 | M8: 1 | N8: =E8*L8*M8 -> 16000 | O8: =H8+K8+N8 -> 40000 | P8: =D8+O8 -> 70000
B9: СПТД | C9: Хайруллина Екатерина Сергеевна | D9: 50000 | F9: 0.4 | G9: 1 | H9: =E9*F9*G9 -> 0 | I9: 0.2 | J9: 1 | K9: =E9*I9*J9 -> 0 | L9: 0.4 | M9: 1 | N9: =E9*L9*M9 -> 0 | O9: =H9+K9+N9 -> 0 | P9: =D9+O9 -> 50000
C10: Рожин Дмитрий Валерьевич | D10: 47619.05 | F10: Отсутствие претензий от РД1 | O10: =H10+K10+N10 -> 0 | P10: =D10+O10 -> 47619.05
B11: водитель-курьер | C11: Костин С.В. | D11: 30000 | E11: 40000 | F11: 1 | G11: 1 | H11: =E11*F11*G11 -> 40000 | N11: =E11*L11*M11 -> 0 | O11: =H11+K11+N11 -> 40000 | P11: =D11+O11 -> 70000
D12: =SUM(D7:D11) -> 205019.05 | O12: =SUM(O7:O11) -> 120000 | P12: =D12+O12 -> 325019.05
O23: =РД!K10 -> 200000
D24: =#REF!+РД!D10+'НК, РГ'!F44+механики!F31+контролеры!D25+'СПТД, курьер'!D12 -> #REF! | O24: ='НК, РГ'!Q23+'НК, РГ'!U44+механики!S18+механики!S19+механики!S29+контролеры!L25+'СПТД, курьер'!O12 -> 1030700 | P24: =#REF!+РД!K10+'НК, РГ'!R23+'НК, РГ'!W44+механики!T18+механики!T29+контролеры!M25+'СПТД, курьер'!P12 -> #REF!
O25: ='НК, РГ'!S23+'НК, РГ'!T23+'НК, РГ'!X44+'НК, РГ'!Y44+'НК, РГ'!Z44 -> 0 | P25: ='НК, РГ'!R23+'НК, РГ'!W44+механики!T18+механики!T29+контролеры!M25+'СПТД, курьер'!P12 -> 2515353.8 | Q25: ФОТ персонала Д4
O26: =O24-O25 -> 1030700 | P26: =РД!K10+#REF! -> #REF! | Q26: ФОТ АУП
O28: =РД!G10+'НК, РГ'!T20+'НК, РГ'!T21+'НК, РГ'!#REF!+'НК, РГ'!#REF!+'НК, РГ'!#REF!+'НК, РГ'!#REF!+'НК, РГ'!#REF!+'НК, РГ'!#REF!+'НК, РГ'!#REF!+'НК, РГ'!#REF!+'НК, РГ'!#REF!+'НК, РГ'!#REF!+'НК, РГ'!#REF!+'НК, РГ'!#REF!+'НК, РГ'!#REF!+механики!S18+механики!S19+контролеры!L18+контролеры!L21+контролеры!L22+контролеры!L23+контролеры!L24+'СПТД, курьер'!O12 -> #REF! | P28: =#REF!+РД!K10+'НК, РГ'!R23+'НК, РГ'!W44-'НК, РГ'!X44-'НК, РГ'!Y44-'НК, РГ'!Z44+механики!T31+контролеры!M25+'СПТД, курьер'!P12 -> #REF!
